{"allTerr":{"5lVTX7":{"q":"5lVTX7","w":1766,"e":"5,77","r":["176104"],"t":{"allObject":{}}},"6ohtu8":{"q":"6ohtu8","w":1766,"e":"5,78","r":["176104"],"t":{"allObject":{}}},"Sv9NN8":{"q":"Sv9NN8","w":1765,"e":"5,79","r":["176104"],"t":{"allObject":{}}},"aMZqne":{"q":"aMZqne","w":1766,"e":"5,80","r":["176104"],"t":{"allObject":{}}},"5i0fQF":{"q":"5i0fQF","w":1765,"e":"6,77","r":["176104"],"t":{"allObject":{}}},"nbbbX0":{"q":"nbbbX0","w":1761,"e":"6,78","r":["176104"],"t":{"allObject":{}}},"EMPyCg":{"q":"EMPyCg","w":1766,"e":"6,80","r":["176104"],"t":{"allObject":{}}},"Jkxaao":{"q":"Jkxaao","w":1765,"e":"7,77","r":["176104"],"t":{"allObject":{}}},"78xsN1":{"q":"78xsN1","w":1764,"e":"7,80","r":["176104"],"t":{"allObject":{}}},"Sr54Pv":{"q":"Sr54Pv","w":1765,"e":"8,77","r":["176104"],"t":{"allObject":{}}},"8Koejz":{"q":"8Koejz","w":1766,"e":"9,77","r":["176104"],"t":{"allObject":{}}},"ABe0C0":{"q":"ABe0C0","w":1766,"e":"9,80","r":["176104"],"t":{"allObject":{}}},"bTRhPU":{"q":"bTRhPU","w":1766,"e":"10,77","r":["176104"],"t":{"allObject":{}}},"kX8qkE":{"q":"kX8qkE","w":1766,"e":"10,78","r":["176104"],"t":{"allObject":{}}},"eFN8d1":{"q":"eFN8d1","w":1766,"e":"10,79","r":["176104"],"t":{"allObject":{}}},"TPJBoT":{"q":"TPJBoT","w":1765,"e":"10,80","r":["176104"],"t":{"allObject":{}}},"UnWWMD":{"q":"UnWWMD","w":1809,"e":"30,128","r":["180104"],"t":{"allObject":{}}},"U8dcbZ":{"q":"U8dcbZ","w":1809,"e":"30,129","r":["180104"],"t":{"allObject":{}}},"vuXnSn":{"q":"vuXnSn","w":1809,"e":"30,130","r":["180104"],"t":{"allObject":{}}},"muay0e":{"q":"muay0e","w":1806,"e":"30,131","r":["180104"],"t":{"allObject":{}}},"XFxd5D":{"q":"XFxd5D","w":1906,"e":"31,115","r":["190104"],"t":{"allObject":{}}},"lqu0oX":{"q":"lqu0oX","w":1905,"e":"31,116","r":["190104"],"t":{"allObject":{}}},"Yj6xXz":{"q":"Yj6xXz","w":1906,"e":"31,117","r":["190104"],"t":{"allObject":{}}},"qkMTSU":{"q":"qkMTSU","w":1905,"e":"31,118","r":["190104"],"t":{"allObject":{}}},"yJ8wiW":{"q":"yJ8wiW","w":1805,"e":"31,128","r":["180104"],"t":{"allObject":{}}},"rsnojD":{"q":"rsnojD","w":1801,"e":"31,129","r":["180104"],"t":{"allObject":{}}},"etEMEB":{"q":"etEMEB","w":1906,"e":"32,115","r":["190104"],"t":{"allObject":{}}},"vv80ly":{"q":"vv80ly","w":1901,"e":"32,116","r":["190104"],"t":{"allObject":{}}},"4TS1TL":{"q":"4TS1TL","w":1905,"e":"32,118","r":["190104"],"t":{"allObject":{}}},"RHEgUg":{"q":"RHEgUg","w":1806,"e":"32,128","r":["180104"],"t":{"allObject":{}}},"GJ3yy8":{"q":"GJ3yy8","w":1807,"e":"32,131","r":["180104"],"t":{"allObject":{}}},"ui0lL1":{"q":"ui0lL1","w":1907,"e":"33,115","r":["190104"],"t":{"allObject":{}}},"kWgEKN":{"q":"kWgEKN","w":1905,"e":"33,118","r":["190104"],"t":{"allObject":{}}},"Oyieor":{"q":"Oyieor","w":1807,"e":"33,131","r":["180104"],"t":{"allObject":{}}},"mfiuyw":{"q":"mfiuyw","w":1787,"e":"34,27","r":["178101"],"t":{"allObject":{}}},"AbBNAv":{"q":"AbBNAv","w":1788,"e":"34,28","r":["178101"],"t":{"allObject":{}}},"tKJQrS":{"q":"tKJQrS","w":1788,"e":"34,29","r":["178101"],"t":{"allObject":{}}},"yAvCPR":{"q":"yAvCPR","w":1787,"e":"34,30","r":["178101"],"t":{"allObject":{}}},"fQ8fya":{"q":"fQ8fya","w":1753,"e":"34,87","r":["175104"],"t":{"allObject":{}}},"IvlMh3":{"q":"IvlMh3","w":1753,"e":"34,88","r":["175104"],"t":{"allObject":{}}},"M0Eoot":{"q":"M0Eoot","w":1753,"e":"34,89","r":["175104"],"t":{"allObject":{}}},"rL13iQ":{"q":"rL13iQ","w":1757,"e":"34,90","r":["175104"],"t":{"allObject":{}}},"OOEV7B":{"q":"OOEV7B","w":1906,"e":"34,115","r":["190104"],"t":{"allObject":{}}},"jttt4t":{"q":"jttt4t","w":1906,"e":"34,118","r":["190104"],"t":{"allObject":{}}},"ruLvKB":{"q":"ruLvKB","w":1809,"e":"34,128","r":["180104"],"t":{"allObject":{}}},"TTdNat":{"q":"TTdNat","w":1805,"e":"34,129","r":["180104"],"t":{"allObject":{}}},"P7dK21":{"q":"P7dK21","w":1805,"e":"34,130","r":["180104"],"t":{"allObject":{}}},"Dce8yB":{"q":"Dce8yB","w":1807,"e":"34,131","r":["180104"],"t":{"allObject":{}}},"ox1XlS":{"q":"ox1XlS","w":1787,"e":"35,27","r":["178101"],"t":{"allObject":{}}},"N6UiTW":{"q":"N6UiTW","w":1781,"e":"35,28","r":["178101"],"t":{"allObject":{}}},"DjWenr":{"q":"DjWenr","w":1788,"e":"35,30","r":["178101"],"t":{"allObject":{}}},"NzioF0":{"q":"NzioF0","w":1755,"e":"35,87","r":["175104"],"t":{"allObject":{}}},"cNdfKO":{"q":"cNdfKO","w":1751,"e":"35,88","r":["175104"],"t":{"allObject":{}}},"WuW6Gu":{"q":"WuW6Gu","w":1905,"e":"35,115","r":["190104"],"t":{"allObject":{}}},"izVwQg":{"q":"izVwQg","w":1907,"e":"35,116","r":["190104"],"t":{"allObject":{}}},"Bs2aYS":{"q":"Bs2aYS","w":1905,"e":"35,117","r":["190104"],"t":{"allObject":{}}},"nx70pc":{"q":"nx70pc","w":1906,"e":"35,118","r":["190104"],"t":{"allObject":{}}},"mQi1oZ":{"q":"mQi1oZ","w":1776,"e":"36,2","r":["177101"],"t":{"allObject":{}}},"oxg9uo":{"q":"oxg9uo","w":1776,"e":"36,3","r":["177101"],"t":{"allObject":{}}},"QJey5T":{"q":"QJey5T","w":1778,"e":"36,4","r":["177101"],"t":{"allObject":{}}},"U8z3As":{"q":"U8z3As","w":1774,"e":"36,5","r":["177101"],"t":{"allObject":{}}},"OSZwmi":{"q":"OSZwmi","w":1787,"e":"36,27","r":["178101"],"t":{"allObject":{}}},"SW7JYG":{"q":"SW7JYG","w":1785,"e":"36,30","r":["178101"],"t":{"allObject":{}}},"9kAE3H":{"q":"9kAE3H","w":1758,"e":"36,90","r":["175104"],"t":{"allObject":{}}},"QMYZan":{"q":"QMYZan","w":1774,"e":"37,2","r":["177101"],"t":{"allObject":{}}},"lZm33d":{"q":"lZm33d","w":1771,"e":"37,3","r":["177101"],"t":{"allObject":{}}},"W7m7lB":{"q":"W7m7lB","w":1775,"e":"37,5","r":["177101"],"t":{"allObject":{}}},"QU6Ibt":{"q":"QU6Ibt","w":1784,"e":"37,27","r":["178101"],"t":{"allObject":{}}},"szSGuD":{"q":"szSGuD","w":1753,"e":"37,87","r":["175104"],"t":{"allObject":{}}},"4TTr3x":{"q":"4TTr3x","w":1773,"e":"38,2","r":["177101"],"t":{"allObject":{}}},"umstzy":{"q":"umstzy","w":1787,"e":"38,27","r":["178101"],"t":{"allObject":{}}},"kLOXGO":{"q":"kLOXGO","w":1787,"e":"38,28","r":["178101"],"t":{"allObject":{}}},"NE0bWv":{"q":"NE0bWv","w":1787,"e":"38,29","r":["178101"],"t":{"allObject":{}}},"X4dak1":{"q":"X4dak1","w":1788,"e":"38,30","r":["178101"],"t":{"allObject":{}}},"ftvd9n":{"q":"ftvd9n","w":1753,"e":"38,87","r":["175104"],"t":{"allObject":{}}},"ooTTq4":{"q":"ooTTq4","w":1753,"e":"38,88","r":["175104"],"t":{"allObject":{}}},"cyBMMt":{"q":"cyBMMt","w":1753,"e":"38,89","r":["175104"],"t":{"allObject":{}}},"CKyEmr":{"q":"CKyEmr","w":1753,"e":"38,90","r":["175104"],"t":{"allObject":{}}},"FUEKP9":{"q":"FUEKP9","w":1778,"e":"40,5","r":["177101"],"t":{"allObject":{}}},"O6Ix2G":{"q":"O6Ix2G","w":1778,"e":"41,2","r":["177101"],"t":{"allObject":{}}},"zTXXvj":{"q":"zTXXvj","w":1776,"e":"41,3","r":["177101"],"t":{"allObject":{}}},"TZdUWy":{"q":"TZdUWy","w":1774,"e":"41,4","r":["177101"],"t":{"allObject":{}}},"M5rIHq":{"q":"M5rIHq","w":1776,"e":"41,5","r":["177101"],"t":{"allObject":{}}},"CshLM3":{"q":"CshLM3","w":1765,"e":"53,67","r":["176101"],"t":{"allObject":{}}},"cJMU7t":{"q":"cJMU7t","w":1765,"e":"53,68","r":["176101"],"t":{"allObject":{}}},"cWgOhC":{"q":"cWgOhC","w":1765,"e":"53,69","r":["176101"],"t":{"allObject":{}}},"AWtm9y":{"q":"AWtm9y","w":1766,"e":"53,70","r":["176101"],"t":{"allObject":{}}},"2UTu2G":{"q":"2UTu2G","w":1766,"e":"54,67","r":["176101"],"t":{"allObject":{}}},"yQhkMH":{"q":"yQhkMH","w":1761,"e":"54,68","r":["176101"],"t":{"allObject":{}}},"pqgwoy":{"q":"pqgwoy","w":1765,"e":"54,70","r":["176101"],"t":{"allObject":{}}},"K8BICQ":{"q":"K8BICQ","w":1765,"e":"55,67","r":["176101"],"t":{"allObject":{}}},"2JGI8F":{"q":"2JGI8F","w":1765,"e":"55,70","r":["176101"],"t":{"allObject":{}}},"6yfPwZ":{"q":"6yfPwZ","w":1764,"e":"56,67","r":["176101"],"t":{"allObject":{}}},"bHMAa6":{"q":"bHMAa6","w":1766,"e":"56,70","r":["176101"],"t":{"allObject":{}}},"mRsNpG":{"q":"mRsNpG","w":1765,"e":"57,70","r":["176101"],"t":{"allObject":{}}},"jle9oQ":{"q":"jle9oQ","w":1766,"e":"58,67","r":["176101"],"t":{"allObject":{}}},"OzcTha":{"q":"OzcTha","w":1765,"e":"58,68","r":["176101"],"t":{"allObject":{}}},"0BRwc4":{"q":"0BRwc4","w":1765,"e":"58,69","r":["176101"],"t":{"allObject":{}}},"dM0CfZ":{"q":"dM0CfZ","w":1766,"e":"58,70","r":["176101"],"t":{"allObject":{}}},"UUBwLK":{"q":"UUBwLK","w":1755,"e":"58,87","r":["175101"],"t":{"allObject":{}}},"Nek0qG":{"q":"Nek0qG","w":1753,"e":"58,88","r":["175101"],"t":{"allObject":{}}},"c88fWl":{"q":"c88fWl","w":1753,"e":"58,89","r":["175101"],"t":{"allObject":{}}},"ozpnAD":{"q":"ozpnAD","w":1754,"e":"58,90","r":["175101"],"t":{"allObject":{}}},"3BLlvA":{"q":"3BLlvA","w":1751,"e":"59,88","r":["175101"],"t":{"allObject":{}}},"HCYP2w":{"q":"HCYP2w","w":1753,"e":"60,87","r":["175101"],"t":{"allObject":{}}},"djqrhF":{"q":"djqrhF","w":1752,"e":"61,87","r":["175101"],"t":{"allObject":{}}},"408njb":{"q":"408njb","w":1753,"e":"62,88","r":["175101"],"t":{"allObject":{}}},"60NKb5":{"q":"60NKb5","w":1753,"e":"62,89","r":["175101"],"t":{"allObject":{}}},"zL6Ap6":{"q":"zL6Ap6","w":1753,"e":"62,90","r":["175101"],"t":{"allObject":{}}},"0jhixY":{"q":"0jhixY","w":1788,"e":"63,110","r":["178104"],"t":{"allObject":{}}},"PsUyQX":{"q":"PsUyQX","w":1788,"e":"63,111","r":["178104"],"t":{"allObject":{}}},"KTTV6A":{"q":"KTTV6A","w":1787,"e":"63,112","r":["178104"],"t":{"allObject":{}}},"HRjtvb":{"q":"HRjtvb","w":1784,"e":"63,113","r":["178104"],"t":{"allObject":{}}},"c9oSqo":{"q":"c9oSqo","w":1787,"e":"64,110","r":["178104"],"t":{"allObject":{}}},"uwUyt9":{"q":"uwUyt9","w":1781,"e":"64,111","r":["178104"],"t":{"allObject":{}}},"iVH2hY":{"q":"iVH2hY","w":1787,"e":"64,113","r":["178104"],"t":{"allObject":{}}},"kM9R0l":{"q":"kM9R0l","w":1784,"e":"65,110","r":["178104"],"t":{"allObject":{}}},"1VBx6u":{"q":"1VBx6u","w":1788,"e":"65,113","r":["178104"],"t":{"allObject":{}}},"Gy53cv":{"q":"Gy53cv","w":1788,"e":"66,110","r":["178104"],"t":{"allObject":{}}},"i9Si0o":{"q":"i9Si0o","w":1788,"e":"66,113","r":["178104"],"t":{"allObject":{}}},"FvaYmo":{"q":"FvaYmo","w":1787,"e":"67,110","r":["178104"],"t":{"allObject":{}}},"6NBsvV":{"q":"6NBsvV","w":1787,"e":"67,111","r":["178104"],"t":{"allObject":{}}},"nl9mXR":{"q":"nl9mXR","w":1787,"e":"67,112","r":["178104"],"t":{"allObject":{}}},"ScuaJ9":{"q":"ScuaJ9","w":1787,"e":"67,113","r":["178104"],"t":{"allObject":{}}},"TgarXk":{"q":"TgarXk","w":1773,"e":"69,136","r":["177104"],"t":{"allObject":{}}},"5AMqmF":{"q":"5AMqmF","w":1778,"e":"69,137","r":["177104"],"t":{"allObject":{}}},"Ixinmi":{"q":"Ixinmi","w":1776,"e":"69,138","r":["177104"],"t":{"allObject":{}}},"OfloTE":{"q":"OfloTE","w":1774,"e":"69,139","r":["177104"],"t":{"allObject":{}}},"nkfIVG":{"q":"nkfIVG","w":1771,"e":"70,137","r":["177104"],"t":{"allObject":{}}},"EfysQA":{"q":"EfysQA","w":1775,"e":"70,139","r":["177104"],"t":{"allObject":{}}},"9eRhkd":{"q":"9eRhkd","w":1778,"e":"72,136","r":["177104"],"t":{"allObject":{}}},"7N4xkp":{"q":"7N4xkp","w":1776,"e":"72,171","r":["177103"],"t":{"allObject":{}}},"yV60wf":{"q":"yV60wf","w":1778,"e":"72,172","r":["177103"],"t":{"allObject":{}}},"Huaigd":{"q":"Huaigd","w":1778,"e":"72,173","r":["177103"],"t":{"allObject":{}}},"TvnSBD":{"q":"TvnSBD","w":1773,"e":"72,174","r":["177103"],"t":{"allObject":{}}},"kyxV1V":{"q":"kyxV1V","w":1776,"e":"73,136","r":["177104"],"t":{"allObject":{}}},"re7Usj":{"q":"re7Usj","w":1778,"e":"73,139","r":["177104"],"t":{"allObject":{}}},"PR0Rs0":{"q":"PR0Rs0","w":1907,"e":"73,163","r":["190103"],"t":{"allObject":{}}},"LRS3Ct":{"q":"LRS3Ct","w":1905,"e":"73,164","r":["190103"],"t":{"allObject":{}}},"aqbws5":{"q":"aqbws5","w":1905,"e":"73,165","r":["190103"],"t":{"allObject":{}}},"bcQkRS":{"q":"bcQkRS","w":1906,"e":"73,166","r":["190103"],"t":{"allObject":{}}},"mPupy9":{"q":"mPupy9","w":1778,"e":"73,171","r":["177103"],"t":{"allObject":{}}},"jP54Bs":{"q":"jP54Bs","w":1771,"e":"73,172","r":["177103"],"t":{"allObject":{}}},"dWAn3X":{"q":"dWAn3X","w":1776,"e":"74,136","r":["177104"],"t":{"allObject":{}}},"QmPHvq":{"q":"QmPHvq","w":1778,"e":"74,137","r":["177104"],"t":{"allObject":{}}},"pE2WZ1":{"q":"pE2WZ1","w":1774,"e":"74,138","r":["177104"],"t":{"allObject":{}}},"jeQbFe":{"q":"jeQbFe","w":1776,"e":"74,139","r":["177104"],"t":{"allObject":{}}},"rziDSD":{"q":"rziDSD","w":1905,"e":"74,163","r":["190103"],"t":{"allObject":{}}},"akEDnp":{"q":"akEDnp","w":1901,"e":"74,164","r":["190103"],"t":{"allObject":{}}},"z93jjG":{"q":"z93jjG","w":1906,"e":"74,166","r":["190103"],"t":{"allObject":{}}},"WaBU0r":{"q":"WaBU0r","w":1778,"e":"74,171","r":["177103"],"t":{"allObject":{}}},"Ig1RF6":{"q":"Ig1RF6","w":3004,"e":"74,196","r":["3004"],"t":{"allObject":{}}},"annlCO":{"q":"annlCO","w":1905,"e":"75,163","r":["190103"],"t":{"allObject":{}}},"vnf8hT":{"q":"vnf8hT","w":1906,"e":"75,166","r":["190103"],"t":{"allObject":{}}},"BBFKLX":{"q":"BBFKLX","w":1774,"e":"75,171","r":["177103"],"t":{"allObject":{}}},"90vvcf":{"q":"90vvcf","w":1774,"e":"75,174","r":["177103"],"t":{"allObject":{}}},"YBzTYi":{"q":"YBzTYi","w":1806,"e":"76,35","r":["180101"],"t":{"allObject":{}}},"VirIs0":{"q":"VirIs0","w":1809,"e":"76,36","r":["180101"],"t":{"allObject":{}}},"cQfz43":{"q":"cQfz43","w":1807,"e":"76,37","r":["180101"],"t":{"allObject":{}}},"aT5Lld":{"q":"aT5Lld","w":1806,"e":"76,38","r":["180101"],"t":{"allObject":{}}},"HmVyYF":{"q":"HmVyYF","w":1907,"e":"76,163","r":["190103"],"t":{"allObject":{}}},"OnRAf9":{"q":"OnRAf9","w":1906,"e":"76,166","r":["190103"],"t":{"allObject":{}}},"MllUaO":{"q":"MllUaO","w":1778,"e":"76,171","r":["177103"],"t":{"allObject":{}}},"sJvGuK":{"q":"sJvGuK","w":1774,"e":"76,174","r":["177103"],"t":{"allObject":{}}},"kGU4Sk":{"q":"kGU4Sk","w":1801,"e":"77,36","r":["180101"],"t":{"allObject":{}}},"lbgInJ":{"q":"lbgInJ","w":1905,"e":"77,163","r":["190103"],"t":{"allObject":{}}},"A1eH9v":{"q":"A1eH9v","w":1906,"e":"77,164","r":["190103"],"t":{"allObject":{}}},"7sBgXA":{"q":"7sBgXA","w":1905,"e":"77,165","r":["190103"],"t":{"allObject":{}}},"Pttvje":{"q":"Pttvje","w":1907,"e":"77,166","r":["190103"],"t":{"allObject":{}}},"1WZTn1":{"q":"1WZTn1","w":1774,"e":"77,171","r":["177103"],"t":{"allObject":{}}},"UGdVe1":{"q":"UGdVe1","w":1778,"e":"77,172","r":["177103"],"t":{"allObject":{}}},"XK5e6z":{"q":"XK5e6z","w":1778,"e":"77,173","r":["177103"],"t":{"allObject":{}}},"hCK0K6":{"q":"hCK0K6","w":1776,"e":"77,174","r":["177103"],"t":{"allObject":{}}},"4E47xj":{"q":"4E47xj","w":1803,"e":"78,35","r":["180101"],"t":{"allObject":{}}},"D6USJv":{"q":"D6USJv","w":1803,"e":"78,38","r":["180101"],"t":{"allObject":{}}},"7YEsPz":{"q":"7YEsPz","w":1809,"e":"80,35","r":["180101"],"t":{"allObject":{}}},"PaOiXE":{"q":"PaOiXE","w":1809,"e":"80,36","r":["180101"],"t":{"allObject":{}}},"HkpxUC":{"q":"HkpxUC","w":1807,"e":"80,37","r":["180101"],"t":{"allObject":{}}},"S2xBSv":{"q":"S2xBSv","w":1807,"e":"80,38","r":["180101"],"t":{"allObject":{}}},"7At7Pu":{"q":"7At7Pu","w":1906,"e":"84,36","r":["190101"],"t":{"allObject":{}}},"zOWOym":{"q":"zOWOym","w":1907,"e":"84,37","r":["190101"],"t":{"allObject":{}}},"kTDimj":{"q":"kTDimj","w":1906,"e":"84,38","r":["190101"],"t":{"allObject":{}}},"vVl2jE":{"q":"vVl2jE","w":1906,"e":"84,39","r":["190101"],"t":{"allObject":{}}},"IemcQM":{"q":"IemcQM","w":1907,"e":"85,36","r":["190101"],"t":{"allObject":{}}},"Wp5Hh9":{"q":"Wp5Hh9","w":1901,"e":"85,37","r":["190101"],"t":{"allObject":{}}},"GFwdbS":{"q":"GFwdbS","w":1908,"e":"85,39","r":["190101"],"t":{"allObject":{}}},"WUSzEE":{"q":"WUSzEE","w":1906,"e":"86,36","r":["190101"],"t":{"allObject":{}}},"OfWRsm":{"q":"OfWRsm","w":1906,"e":"87,36","r":["190101"],"t":{"allObject":{}}},"RYrwmj":{"q":"RYrwmj","w":1907,"e":"87,39","r":["190101"],"t":{"allObject":{}}},"k9OsI7":{"q":"k9OsI7","w":1905,"e":"88,36","r":["190101"],"t":{"allObject":{}}},"6wMFLd":{"q":"6wMFLd","w":1905,"e":"88,37","r":["190101"],"t":{"allObject":{}}},"HPoump":{"q":"HPoump","w":1905,"e":"88,38","r":["190101"],"t":{"allObject":{}}},"2BqvdV":{"q":"2BqvdV","w":1907,"e":"88,39","r":["190101"],"t":{"allObject":{}}},"B98YDp":{"q":"B98YDp","w":1805,"e":"99,131","r":["180103"],"t":{"allObject":{}}},"tvNc6m":{"q":"tvNc6m","w":1809,"e":"99,132","r":["180103"],"t":{"allObject":{}}},"Rq0Gna":{"q":"Rq0Gna","w":1805,"e":"99,133","r":["180103"],"t":{"allObject":{}}},"f6CMbw":{"q":"f6CMbw","w":1803,"e":"99,134","r":["180103"],"t":{"allObject":{}}},"JuJ5aw":{"q":"JuJ5aw","w":1806,"e":"100,131","r":["180103"],"t":{"allObject":{}}},"H5VcFO":{"q":"H5VcFO","w":1801,"e":"100,132","r":["180103"],"t":{"allObject":{}}},"91Hmly":{"q":"91Hmly","w":1806,"e":"101,134","r":["180103"],"t":{"allObject":{}}},"FtGzeM":{"q":"FtGzeM","w":1809,"e":"102,131","r":["180103"],"t":{"allObject":{}}},"pdp1Pj":{"q":"pdp1Pj","w":1765,"e":"102,184","r":["176103"],"t":{"allObject":{}}},"W9Aunh":{"q":"W9Aunh","w":1766,"e":"102,185","r":["176103"],"t":{"allObject":{}}},"ZaD7yQ":{"q":"ZaD7yQ","w":1766,"e":"102,186","r":["176103"],"t":{"allObject":{}}},"eLD1H8":{"q":"eLD1H8","w":1765,"e":"102,187","r":["176103"],"t":{"allObject":{}}},"XbDmSZ":{"q":"XbDmSZ","w":1807,"e":"103,131","r":["180103"],"t":{"allObject":{}}},"FiR2X8":{"q":"FiR2X8","w":1805,"e":"103,132","r":["180103"],"t":{"allObject":{}}},"3MxhxH":{"q":"3MxhxH","w":1805,"e":"103,133","r":["180103"],"t":{"allObject":{}}},"9eWauI":{"q":"9eWauI","w":1809,"e":"103,134","r":["180103"],"t":{"allObject":{}}},"LK9FJA":{"q":"LK9FJA","w":1766,"e":"103,184","r":["176103"],"t":{"allObject":{}}},"DlVsyV":{"q":"DlVsyV","w":1761,"e":"103,185","r":["176103"],"t":{"allObject":{}}},"tSv1ZK":{"q":"tSv1ZK","w":1765,"e":"103,187","r":["176103"],"t":{"allObject":{}}},"swJHTY":{"q":"swJHTY","w":1766,"e":"104,184","r":["176103"],"t":{"allObject":{}}},"Hbi83b":{"q":"Hbi83b","w":1766,"e":"104,187","r":["176103"],"t":{"allObject":{}}},"7xJTu5":{"q":"7xJTu5","w":1766,"e":"105,184","r":["176103"],"t":{"allObject":{}}},"X0J3gs":{"q":"X0J3gs","w":1764,"e":"105,187","r":["176103"],"t":{"allObject":{}}},"aJ5NSp":{"q":"aJ5NSp","w":1757,"e":"106,142","r":["175103"],"t":{"allObject":{}}},"eOPx9Y":{"q":"eOPx9Y","w":1753,"e":"106,143","r":["175103"],"t":{"allObject":{}}},"2RD48r":{"q":"2RD48r","w":1753,"e":"106,144","r":["175103"],"t":{"allObject":{}}},"fH1phx":{"q":"fH1phx","w":1757,"e":"106,145","r":["175103"],"t":{"allObject":{}}},"YMg3uZ":{"q":"YMg3uZ","w":1766,"e":"106,184","r":["176103"],"t":{"allObject":{}}},"Qlvhgn":{"q":"Qlvhgn","w":1751,"e":"107,143","r":["175103"],"t":{"allObject":{}}},"S2s9yz":{"q":"S2s9yz","w":1765,"e":"107,184","r":["176103"],"t":{"allObject":{}}},"fSvSFe":{"q":"fSvSFe","w":1765,"e":"107,185","r":["176103"],"t":{"allObject":{}}},"kwWvHM":{"q":"kwWvHM","w":1766,"e":"107,186","r":["176103"],"t":{"allObject":{}}},"xWsPLc":{"q":"xWsPLc","w":1765,"e":"107,187","r":["176103"],"t":{"allObject":{}}},"5pd1zJ":{"q":"5pd1zJ","w":1758,"e":"108,142","r":["175103"],"t":{"allObject":{}}},"LDMNkU":{"q":"LDMNkU","w":1753,"e":"108,145","r":["175103"],"t":{"allObject":{}}},"2hzU6r":{"q":"2hzU6r","w":1752,"e":"109,145","r":["175103"],"t":{"allObject":{}}},"95DSAT":{"q":"95DSAT","w":1753,"e":"110,142","r":["175103"],"t":{"allObject":{}}},"KFrB5d":{"q":"KFrB5d","w":1753,"e":"110,143","r":["175103"],"t":{"allObject":{}}},"DWo1R6":{"q":"DWo1R6","w":1753,"e":"110,144","r":["175103"],"t":{"allObject":{}}},"Ibeu3Q":{"q":"Ibeu3Q","w":2901,"e":"122,79","r":["2901"],"t":{"allObject":{}}},"RZz66a":{"q":"RZz66a","w":1784,"e":"124,129","r":["178103"],"t":{"allObject":{}}},"hfYOSN":{"q":"hfYOSN","w":1788,"e":"124,130","r":["178103"],"t":{"allObject":{}}},"pzNiou":{"q":"pzNiou","w":1787,"e":"124,131","r":["178103"],"t":{"allObject":{}}},"b6KbSh":{"q":"b6KbSh","w":1787,"e":"124,132","r":["178103"],"t":{"allObject":{}}},"iWsn0O":{"q":"iWsn0O","w":1787,"e":"125,129","r":["178103"],"t":{"allObject":{}}},"QeWSO1":{"q":"QeWSO1","w":1781,"e":"125,130","r":["178103"],"t":{"allObject":{}}},"XVL3kJ":{"q":"XVL3kJ","w":1784,"e":"125,132","r":["178103"],"t":{"allObject":{}}},"iT1AKZ":{"q":"iT1AKZ","w":1787,"e":"126,129","r":["178103"],"t":{"allObject":{}}},"uaH7z8":{"q":"uaH7z8","w":1784,"e":"126,132","r":["178103"],"t":{"allObject":{}}},"zJIRN4":{"q":"zJIRN4","w":1788,"e":"127,129","r":["178103"],"t":{"allObject":{}}},"92g8Il":{"q":"92g8Il","w":1784,"e":"127,132","r":["178103"],"t":{"allObject":{}}},"VBsiDD":{"q":"VBsiDD","w":1787,"e":"128,129","r":["178103"],"t":{"allObject":{}}},"F5FQHI":{"q":"F5FQHI","w":1788,"e":"128,130","r":["178103"],"t":{"allObject":{}}},"mBxKKN":{"q":"mBxKKN","w":1784,"e":"128,131","r":["178103"],"t":{"allObject":{}}},"3TzTe2":{"q":"3TzTe2","w":1787,"e":"128,132","r":["178103"],"t":{"allObject":{}}},"zK9N5m":{"q":"zK9N5m","w":1766,"e":"135,31","r":["176102"],"t":{"allObject":{}}},"dp7In4":{"q":"dp7In4","w":1766,"e":"135,32","r":["176102"],"t":{"allObject":{}}},"l9BRln":{"q":"l9BRln","w":1766,"e":"135,33","r":["176102"],"t":{"allObject":{}}},"zlQQGQ":{"q":"zlQQGQ","w":1766,"e":"135,34","r":["176102"],"t":{"allObject":{}}},"PjpJTE":{"q":"PjpJTE","w":1766,"e":"136,31","r":["176102"],"t":{"allObject":{}}},"0L6zn6":{"q":"0L6zn6","w":1761,"e":"136,32","r":["176102"],"t":{"allObject":{}}},"Gm0NNj":{"q":"Gm0NNj","w":1765,"e":"136,34","r":["176102"],"t":{"allObject":{}}},"Akp1pL":{"q":"Akp1pL","w":1765,"e":"137,31","r":["176102"],"t":{"allObject":{}}},"WmV5Xz":{"q":"WmV5Xz","w":1766,"e":"137,34","r":["176102"],"t":{"allObject":{}}},"2lE8GF":{"q":"2lE8GF","w":1766,"e":"138,31","r":["176102"],"t":{"allObject":{}}},"JVt5Oy":{"q":"JVt5Oy","w":1765,"e":"138,34","r":["176102"],"t":{"allObject":{}}},"80Pem3":{"q":"80Pem3","w":1766,"e":"139,31","r":["176102"],"t":{"allObject":{}}},"nCZZmi":{"q":"nCZZmi","w":1765,"e":"139,34","r":["176102"],"t":{"allObject":{}}},"wZIJHH":{"q":"wZIJHH","w":1765,"e":"140,31","r":["176102"],"t":{"allObject":{}}},"hT9S2Y":{"q":"hT9S2Y","w":1766,"e":"140,32","r":["176102"],"t":{"allObject":{}}},"3JavOE":{"q":"3JavOE","w":1765,"e":"140,33","r":["176102"],"t":{"allObject":{}}},"SJoR3a":{"q":"SJoR3a","w":1765,"e":"140,34","r":["176102"],"t":{"allObject":{}}},"PoQrY9":{"q":"PoQrY9","w":1905,"e":"142,26","r":["190102"],"t":{"allObject":{}}},"qo4yy6":{"q":"qo4yy6","w":1905,"e":"142,27","r":["190102"],"t":{"allObject":{}}},"U0IHGR":{"q":"U0IHGR","w":1907,"e":"142,28","r":["190102"],"t":{"allObject":{}}},"ivIRpo":{"q":"ivIRpo","w":1905,"e":"142,29","r":["190102"],"t":{"allObject":{}}},"LEFJIo":{"q":"LEFJIo","w":1905,"e":"143,26","r":["190102"],"t":{"allObject":{}}},"9NqiIj":{"q":"9NqiIj","w":1901,"e":"143,27","r":["190102"],"t":{"allObject":{}}},"GD00cZ":{"q":"GD00cZ","w":1905,"e":"143,29","r":["190102"],"t":{"allObject":{}}},"DVcghO":{"q":"DVcghO","w":1785,"e":"143,54","r":["178102"],"t":{"allObject":{}}},"67EyyU":{"q":"67EyyU","w":1788,"e":"143,55","r":["178102"],"t":{"allObject":{}}},"eY9eSR":{"q":"eY9eSR","w":1784,"e":"143,56","r":["178102"],"t":{"allObject":{}}},"cPqXiU":{"q":"cPqXiU","w":1784,"e":"143,57","r":["178102"],"t":{"allObject":{}}},"yp2qQE":{"q":"yp2qQE","w":1906,"e":"144,26","r":["190102"],"t":{"allObject":{}}},"ToQn2F":{"q":"ToQn2F","w":1907,"e":"144,29","r":["190102"],"t":{"allObject":{}}},"vfBTXS":{"q":"vfBTXS","w":1781,"e":"144,55","r":["178102"],"t":{"allObject":{}}},"ue3ZTE":{"q":"ue3ZTE","w":1787,"e":"144,57","r":["178102"],"t":{"allObject":{}}},"kvQ7Gs":{"q":"kvQ7Gs","w":1907,"e":"145,26","r":["190102"],"t":{"allObject":{}}},"42mgPY":{"q":"42mgPY","w":1907,"e":"145,29","r":["190102"],"t":{"allObject":{}}},"Ky60w8":{"q":"Ky60w8","w":1784,"e":"145,54","r":["178102"],"t":{"allObject":{}}},"UfFchi":{"q":"UfFchi","w":1788,"e":"145,57","r":["178102"],"t":{"allObject":{}}},"hjnGnT":{"q":"hjnGnT","w":1907,"e":"146,26","r":["190102"],"t":{"allObject":{}}},"GSynlF":{"q":"GSynlF","w":1905,"e":"146,27","r":["190102"],"t":{"allObject":{}}},"WOXN6Q":{"q":"WOXN6Q","w":1905,"e":"146,28","r":["190102"],"t":{"allObject":{}}},"BItKbm":{"q":"BItKbm","w":1906,"e":"146,29","r":["190102"],"t":{"allObject":{}}},"HuW5Fq":{"q":"HuW5Fq","w":1788,"e":"146,54","r":["178102"],"t":{"allObject":{}}},"n7IrJi":{"q":"n7IrJi","w":1784,"e":"146,57","r":["178102"],"t":{"allObject":{}}},"vgEcq8":{"q":"vgEcq8","w":1788,"e":"147,54","r":["178102"],"t":{"allObject":{}}},"aevl9L":{"q":"aevl9L","w":1787,"e":"147,55","r":["178102"],"t":{"allObject":{}}},"fklFNi":{"q":"fklFNi","w":1787,"e":"147,56","r":["178102"],"t":{"allObject":{}}},"RB400L":{"q":"RB400L","w":1787,"e":"147,57","r":["178102"],"t":{"allObject":{}}},"EZ8TQv":{"q":"EZ8TQv","w":1774,"e":"155,1","r":["177102"],"t":{"allObject":{}}},"Uo2vsJ":{"q":"Uo2vsJ","w":1774,"e":"155,2","r":["177102"],"t":{"allObject":{}}},"8dkukX":{"q":"8dkukX","w":1774,"e":"155,3","r":["177102"],"t":{"allObject":{}}},"RiolJu":{"q":"RiolJu","w":1778,"e":"155,4","r":["177102"],"t":{"allObject":{}}},"lsipM3":{"q":"lsipM3","w":1776,"e":"156,1","r":["177102"],"t":{"allObject":{}}},"gbhxlU":{"q":"gbhxlU","w":1771,"e":"156,2","r":["177102"],"t":{"allObject":{}}},"0ue0sM":{"q":"0ue0sM","w":1778,"e":"156,4","r":["177102"],"t":{"allObject":{}}},"w2YwHv":{"q":"w2YwHv","w":1773,"e":"157,1","r":["177102"],"t":{"allObject":{}}},"mujo6e":{"q":"mujo6e","w":1778,"e":"157,4","r":["177102"],"t":{"allObject":{}}},"zZEwVN":{"q":"zZEwVN","w":2501,"e":"157,71","r":["2501"],"t":{"allObject":{}}},"HuO9On":{"q":"HuO9On","w":1773,"e":"158,4","r":["177102"],"t":{"allObject":{}}},"sD4suS":{"q":"sD4suS","w":2502,"e":"158,68","r":["2502"],"t":{"allObject":{}}},"3R6OKM":{"q":"3R6OKM","w":2501,"e":"158,69","r":["2501"],"t":{"allObject":{}}},"wJCcz4":{"q":"wJCcz4","w":2503,"e":"158,70","r":["2503"],"t":{"allObject":{}}},"DY2DQM":{"q":"DY2DQM","w":2701,"e":"158,71","r":["2701"],"t":{"allObject":{}}},"RoARxY":{"q":"RoARxY","w":2501,"e":"159,65","r":["2501"],"t":{"allObject":{}}},"KelJ1E":{"q":"KelJ1E","w":2502,"e":"159,66","r":["2502"],"t":{"allObject":{}}},"3GQtj3":{"q":"3GQtj3","w":2501,"e":"159,67","r":["2501"],"t":{"allObject":{}}},"usWf0Y":{"q":"usWf0Y","w":2703,"e":"159,68","r":["2703"],"t":{"allObject":{}}},"RrvHcR":{"q":"RrvHcR","w":2704,"e":"159,69","r":["2704"],"t":{"allObject":{}}},"7NDri8":{"q":"7NDri8","w":2701,"e":"159,71","r":["2701"],"t":{"allObject":{}}},"WnZ12n":{"q":"WnZ12n","w":1774,"e":"160,1","r":["177102"],"t":{"allObject":{}}},"jAML4y":{"q":"jAML4y","w":1774,"e":"160,2","r":["177102"],"t":{"allObject":{}}},"3kN0jM":{"q":"3kN0jM","w":1774,"e":"160,3","r":["177102"],"t":{"allObject":{}}},"BqoTQK":{"q":"BqoTQK","w":2504,"e":"160,62","r":["2504"],"t":{"allObject":{}}},"LWjhXw":{"q":"LWjhXw","w":2503,"e":"160,63","r":["2503"],"t":{"allObject":{}}},"1NjEr3":{"q":"1NjEr3","w":2502,"e":"160,64","r":["2502"],"t":{"allObject":{}}},"ojxF7m":{"q":"ojxF7m","w":2703,"e":"160,65","r":["2703"],"t":{"allObject":{}}},"jxaKVT":{"q":"jxaKVT","w":2701,"e":"160,66","r":["2701"],"t":{"allObject":{}}},"g8lvUI":{"q":"g8lvUI","w":2701,"e":"160,67","r":["2701"],"t":{"allObject":{}}},"N7nEom":{"q":"N7nEom","w":2702,"e":"160,68","r":["2702"],"t":{"allObject":{}}},"IW19wt":{"q":"IW19wt","w":2703,"e":"160,71","r":["2703"],"t":{"allObject":{}}},"mmFuqQ":{"q":"mmFuqQ","w":1804,"e":"161,28","r":["180102"],"t":{"allObject":{}}},"hAtzNH":{"q":"hAtzNH","w":1807,"e":"161,29","r":["180102"],"t":{"allObject":{}}},"jWgdQV":{"q":"jWgdQV","w":1809,"e":"161,30","r":["180102"],"t":{"allObject":{}}},"zTLpgi":{"q":"zTLpgi","w":1806,"e":"161,31","r":["180102"],"t":{"allObject":{}}},"RuO5Y6":{"q":"RuO5Y6","w":2501,"e":"161,60","r":["2501"],"t":{"allObject":{}}},"9kLYei":{"q":"9kLYei","w":2502,"e":"161,61","r":["2502"],"t":{"allObject":{}}},"1OulI7":{"q":"1OulI7","w":2704,"e":"161,62","r":["2704"],"t":{"allObject":{}}},"fhooCi":{"q":"fhooCi","w":2701,"e":"161,64","r":["2701"],"t":{"allObject":{}}},"AtQrHB":{"q":"AtQrHB","w":2702,"e":"161,65","r":["2702"],"t":{"allObject":{}}},"DHSje5":{"q":"DHSje5","w":2705,"e":"161,66","r":["2705"],"t":{"allObject":{}}},"2xTpcj":{"q":"2xTpcj","w":2701,"e":"161,69","r":["2701"],"t":{"allObject":{}}},"7apIv3":{"q":"7apIv3","w":2703,"e":"161,70","r":["2703"],"t":{"allObject":{}}},"1Q8C79":{"q":"1Q8C79","w":2701,"e":"161,71","r":["2701"],"t":{"allObject":{}}},"9tSsxa":{"q":"9tSsxa","w":1801,"e":"162,29","r":["180102"],"t":{"allObject":{}}},"6ye64D":{"q":"6ye64D","w":2503,"e":"162,59","r":["2503"],"t":{"allObject":{}}},"CPhd1V":{"q":"CPhd1V","w":2702,"e":"162,60","r":["2702"],"t":{"allObject":{}}},"2T53dx":{"q":"2T53dx","w":2701,"e":"162,61","r":["2701"],"t":{"allObject":{}}},"8ElIfG":{"q":"8ElIfG","w":2704,"e":"162,64","r":["2704"],"t":{"allObject":{}}},"M1ZDl9":{"q":"M1ZDl9","w":2701,"e":"162,69","r":["2701"],"t":{"allObject":{}}},"lJ0rgJ":{"q":"lJ0rgJ","w":2703,"e":"162,70","r":["2703"],"t":{"allObject":{}}},"FQkBcf":{"q":"FQkBcf","w":2703,"e":"162,71","r":["2703"],"t":{"allObject":{}}},"FGAat3":{"q":"FGAat3","w":1756,"e":"163,1","r":["175102"],"t":{"allObject":{}}},"TU3wfl":{"q":"TU3wfl","w":1753,"e":"163,2","r":["175102"],"t":{"allObject":{}}},"3b2FyR":{"q":"3b2FyR","w":1753,"e":"163,3","r":["175102"],"t":{"allObject":{}}},"3Pqk4p":{"q":"3Pqk4p","w":1752,"e":"163,4","r":["175102"],"t":{"allObject":{}}},"VBMggs":{"q":"VBMggs","w":1808,"e":"163,28","r":["180102"],"t":{"allObject":{}}},"RaJY5N":{"q":"RaJY5N","w":1809,"e":"163,31","r":["180102"],"t":{"allObject":{}}},"TnVwId":{"q":"TnVwId","w":2504,"e":"163,57","r":["2504"],"t":{"allObject":{}}},"YKfKs1":{"q":"YKfKs1","w":2501,"e":"163,58","r":["2501"],"t":{"allObject":{}}},"N0tftd":{"q":"N0tftd","w":2704,"e":"163,59","r":["2704"],"t":{"allObject":{}}},"DyCaFU":{"q":"DyCaFU","w":2705,"e":"163,61","r":["2705"],"t":{"allObject":{}}},"eqwKBE":{"q":"eqwKBE","w":2705,"e":"163,69","r":["2705"],"t":{"allObject":{}}},"wv4rPj":{"q":"wv4rPj","w":1751,"e":"164,2","r":["175102"],"t":{"allObject":{}}},"kqWnss":{"q":"kqWnss","w":1806,"e":"164,31","r":["180102"],"t":{"allObject":{}}},"7YvpJg":{"q":"7YvpJg","w":2501,"e":"164,56","r":["2501"],"t":{"allObject":{}}},"UMUf3N":{"q":"UMUf3N","w":2702,"e":"164,57","r":["2702"],"t":{"allObject":{}}},"RtsJ0j":{"q":"RtsJ0j","w":2702,"e":"164,58","r":["2702"],"t":{"allObject":{}}},"An4smm":{"q":"An4smm","w":2703,"e":"164,64","r":["2703"],"t":{"allObject":{}}},"751n7T":{"q":"751n7T","w":2702,"e":"164,65","r":["2702"],"t":{"allObject":{}}},"sB5xfO":{"q":"sB5xfO","w":2702,"e":"164,66","r":["2702"],"t":{"allObject":{}}},"X3AbA9":{"q":"X3AbA9","w":2702,"e":"164,67","r":["2702"],"t":{"allObject":{}}},"7b4yqg":{"q":"7b4yqg","w":2701,"e":"164,68","r":["2701"],"t":{"allObject":{}}},"YwqXgb":{"q":"YwqXgb","w":1753,"e":"165,4","r":["175102"],"t":{"allObject":{}}},"kCH8dC":{"q":"kCH8dC","w":1805,"e":"165,28","r":["180102"],"t":{"allObject":{}}},"bLrWEy":{"q":"bLrWEy","w":1805,"e":"165,29","r":["180102"],"t":{"allObject":{}}},"tZ1e7I":{"q":"tZ1e7I","w":1809,"e":"165,30","r":["180102"],"t":{"allObject":{}}},"uVf6gW":{"q":"uVf6gW","w":2501,"e":"165,54","r":["2501"],"t":{"allObject":{}}},"6wtSlt":{"q":"6wtSlt","w":2503,"e":"165,55","r":["2503"],"t":{"allObject":{}}},"fJzUEL":{"q":"fJzUEL","w":2703,"e":"165,56","r":["2703"],"t":{"allObject":{}}},"3BHm03":{"q":"3BHm03","w":2705,"e":"165,57","r":["2705"],"t":{"allObject":{}}},"t5xNWI":{"q":"t5xNWI","w":2701,"e":"165,60","r":["2701"],"t":{"allObject":{}}},"nfyZnK":{"q":"nfyZnK","w":2704,"e":"165,64","r":["2704"],"t":{"allObject":{}}},"AvjFWS":{"q":"AvjFWS","w":2705,"e":"165,66","r":["2705"],"t":{"allObject":{}}},"2da9Bv":{"q":"2da9Bv","w":1758,"e":"166,4","r":["175102"],"t":{"allObject":{}}},"cBJoao":{"q":"cBJoao","w":2504,"e":"166,53","r":["2504"],"t":{"allObject":{}}},"2jBxqz":{"q":"2jBxqz","w":2702,"e":"166,54","r":["2702"],"t":{"allObject":{}}},"KuMVBY":{"q":"KuMVBY","w":2701,"e":"166,55","r":["2701"],"t":{"allObject":{}}},"0Xee7J":{"q":"0Xee7J","w":2702,"e":"166,56","r":["2702"],"t":{"allObject":{}}},"sgCR9V":{"q":"sgCR9V","w":2703,"e":"166,60","r":["2703"],"t":{"allObject":{}}},"Lui9ff":{"q":"Lui9ff","w":2701,"e":"166,61","r":["2701"],"t":{"allObject":{}}},"1JE7wI":{"q":"1JE7wI","w":2704,"e":"166,62","r":["2704"],"t":{"allObject":{}}},"4MC77y":{"q":"4MC77y","w":2702,"e":"166,69","r":["2702"],"t":{"allObject":{}}},"ctHy0R":{"q":"ctHy0R","w":2701,"e":"166,70","r":["2701"],"t":{"allObject":{}}},"ZLw076":{"q":"ZLw076","w":2701,"e":"166,71","r":["2701"],"t":{"allObject":{}}},"FblQe5":{"q":"FblQe5","w":1753,"e":"167,1","r":["175102"],"t":{"allObject":{}}},"DL3vuI":{"q":"DL3vuI","w":1753,"e":"167,2","r":["175102"],"t":{"allObject":{}}},"ER3Xpu":{"q":"ER3Xpu","w":1753,"e":"167,3","r":["175102"],"t":{"allObject":{}}},"6hkmLr":{"q":"6hkmLr","w":2503,"e":"167,52","r":["2503"],"t":{"allObject":{}}},"IbithC":{"q":"IbithC","w":2703,"e":"167,53","r":["2703"],"t":{"allObject":{}}},"D1ZIlf":{"q":"D1ZIlf","w":2702,"e":"167,54","r":["2702"],"t":{"allObject":{}}},"N47wzg":{"q":"N47wzg","w":2702,"e":"167,55","r":["2702"],"t":{"allObject":{}}},"f09Oe6":{"q":"f09Oe6","w":2701,"e":"167,56","r":["2701"],"t":{"allObject":{}}},"A0z5TJ":{"q":"A0z5TJ","w":2704,"e":"167,60","r":["2704"],"t":{"allObject":{}}},"GNyH3h":{"q":"GNyH3h","w":2702,"e":"167,64","r":["2702"],"t":{"allObject":{}}},"Vlfiah":{"q":"Vlfiah","w":2701,"e":"167,65","r":["2701"],"t":{"allObject":{}}},"b5XH6j":{"q":"b5XH6j","w":2704,"e":"167,69","r":["2704"],"t":{"allObject":{}}},"pr6EDL":{"q":"pr6EDL","w":2703,"e":"167,71","r":["2703"],"t":{"allObject":{}}},"y0XsZh":{"q":"y0XsZh","w":2502,"e":"168,51","r":["2502"],"t":{"allObject":{}}},"sKcE4X":{"q":"sKcE4X","w":2705,"e":"168,52","r":["2705"],"t":{"allObject":{}}},"OPQKTW":{"q":"OPQKTW","w":2705,"e":"168,55","r":["2705"],"t":{"allObject":{}}},"WYMZXo":{"q":"WYMZXo","w":2701,"e":"168,58","r":["2701"],"t":{"allObject":{}}},"s5RRXs":{"q":"s5RRXs","w":2702,"e":"168,59","r":["2702"],"t":{"allObject":{}}},"CSSDz4":{"q":"CSSDz4","w":2703,"e":"168,62","r":["2703"],"t":{"allObject":{}}},"XcN86L":{"q":"XcN86L","w":2702,"e":"168,63","r":["2702"],"t":{"allObject":{}}},"4xWQIc":{"q":"4xWQIc","w":2705,"e":"168,64","r":["2705"],"t":{"allObject":{}}},"hLM5WU":{"q":"hLM5WU","w":2702,"e":"168,67","r":["2702"],"t":{"allObject":{}}},"4Dhv0N":{"q":"4Dhv0N","w":2703,"e":"168,68","r":["2703"],"t":{"allObject":{}}},"so7Akl":{"q":"so7Akl","w":2702,"e":"168,71","r":["2702"],"t":{"allObject":{}}},"O6MU7L":{"q":"O6MU7L","w":2503,"e":"169,50","r":["2503"],"t":{"allObject":{}}},"dTAUMa":{"q":"dTAUMa","w":2702,"e":"169,51","r":["2702"],"t":{"allObject":{}}},"uabLBE":{"q":"uabLBE","w":2704,"e":"169,58","r":["2704"],"t":{"allObject":{}}},"DqPYZi":{"q":"DqPYZi","w":2705,"e":"169,60","r":["2705"],"t":{"allObject":{}}},"GocQCV":{"q":"GocQCV","w":2702,"e":"169,63","r":["2702"],"t":{"allObject":{}}},"VlEZ3D":{"q":"VlEZ3D","w":2701,"e":"169,67","r":["2701"],"t":{"allObject":{}}},"CoCUL8":{"q":"CoCUL8","w":2702,"e":"169,68","r":["2702"],"t":{"allObject":{}}},"7bvTJN":{"q":"7bvTJN","w":2701,"e":"169,69","r":["2701"],"t":{"allObject":{}}},"sZS49J":{"q":"sZS49J","w":2701,"e":"169,70","r":["2701"],"t":{"allObject":{}}},"oRs23N":{"q":"oRs23N","w":2701,"e":"169,71","r":["2701"],"t":{"allObject":{}}},"idlbzk":{"q":"idlbzk","w":2504,"e":"170,49","r":["2504"],"t":{"allObject":{}}},"iDls7n":{"q":"iDls7n","w":2702,"e":"170,50","r":["2702"],"t":{"allObject":{}}},"kYODOu":{"q":"kYODOu","w":2703,"e":"170,51","r":["2703"],"t":{"allObject":{}}},"cPLVNW":{"q":"cPLVNW","w":2703,"e":"170,63","r":["2703"],"t":{"allObject":{}}},"Srxccn":{"q":"Srxccn","w":2704,"e":"170,67","r":["2704"],"t":{"allObject":{}}},"atj8pj":{"q":"atj8pj","w":2705,"e":"170,69","r":["2705"],"t":{"allObject":{}}},"GORYiR":{"q":"GORYiR","w":2501,"e":"171,48","r":["2501"],"t":{"allObject":{}}},"j0BVD3":{"q":"j0BVD3","w":2705,"e":"171,49","r":["2705"],"t":{"allObject":{}}},"OC5YUz":{"q":"OC5YUz","w":2701,"e":"171,52","r":["2701"],"t":{"allObject":{}}},"YAFjsJ":{"q":"YAFjsJ","w":2703,"e":"171,53","r":["2703"],"t":{"allObject":{}}},"7cq4We":{"q":"7cq4We","w":2703,"e":"171,54","r":["2703"],"t":{"allObject":{}}},"Oxue9Q":{"q":"Oxue9Q","w":2702,"e":"171,55","r":["2702"],"t":{"allObject":{}}},"ejsGjN":{"q":"ejsGjN","w":2702,"e":"171,56","r":["2702"],"t":{"allObject":{}}},"gmK2fq":{"q":"gmK2fq","w":2701,"e":"171,57","r":["2701"],"t":{"allObject":{}}},"5tB72N":{"q":"5tB72N","w":2701,"e":"171,58","r":["2701"],"t":{"allObject":{}}},"eoibOv":{"q":"eoibOv","w":2702,"e":"171,59","r":["2702"],"t":{"allObject":{}}},"dv96Gw":{"q":"dv96Gw","w":2701,"e":"171,63","r":["2701"],"t":{"allObject":{}}},"CjV4fM":{"q":"CjV4fM","w":2702,"e":"171,64","r":["2702"],"t":{"allObject":{}}},"O2rnEv":{"q":"O2rnEv","w":2703,"e":"171,65","r":["2703"],"t":{"allObject":{}}},"0TIQ0u":{"q":"0TIQ0u","w":2702,"e":"171,66","r":["2702"],"t":{"allObject":{}}},"TS4I0q":{"q":"TS4I0q","w":2502,"e":"172,47","r":["2502"],"t":{"allObject":{}}},"ehond5":{"q":"ehond5","w":2703,"e":"172,48","r":["2703"],"t":{"allObject":{}}},"qlsmu8":{"q":"qlsmu8","w":2703,"e":"172,52","r":["2703"],"t":{"allObject":{}}},"RQ19nQ":{"q":"RQ19nQ","w":2705,"e":"172,53","r":["2705"],"t":{"allObject":{}}},"6gycnR":{"q":"6gycnR","w":2703,"e":"172,56","r":["2703"],"t":{"allObject":{}}},"gdbw2E":{"q":"gdbw2E","w":2705,"e":"172,57","r":["2705"],"t":{"allObject":{}}},"oFk7w9":{"q":"oFk7w9","w":2702,"e":"172,60","r":["2702"],"t":{"allObject":{}}},"2ZGpNZ":{"q":"2ZGpNZ","w":2701,"e":"172,61","r":["2701"],"t":{"allObject":{}}},"APoA89":{"q":"APoA89","w":2701,"e":"172,62","r":["2701"],"t":{"allObject":{}}},"hYV3DX":{"q":"hYV3DX","w":2703,"e":"172,63","r":["2703"],"t":{"allObject":{}}},"5k1tPQ":{"q":"5k1tPQ","w":2704,"e":"172,64","r":["2704"],"t":{"allObject":{}}},"I92oJL":{"q":"I92oJL","w":2701,"e":"172,66","r":["2701"],"t":{"allObject":{}}},"JUp3Iy":{"q":"JUp3Iy","w":2702,"e":"172,67","r":["2702"],"t":{"allObject":{}}},"cCJDag":{"q":"cCJDag","w":2702,"e":"172,68","r":["2702"],"t":{"allObject":{}}},"ytgncc":{"q":"ytgncc","w":2501,"e":"173,46","r":["2501"],"t":{"allObject":{}}},"hhQVEz":{"q":"hhQVEz","w":2701,"e":"173,47","r":["2701"],"t":{"allObject":{}}},"IVPGwM":{"q":"IVPGwM","w":2702,"e":"173,48","r":["2702"],"t":{"allObject":{}}},"ws3H51":{"q":"ws3H51","w":2703,"e":"173,52","r":["2703"],"t":{"allObject":{}}},"Nb92I2":{"q":"Nb92I2","w":2701,"e":"173,56","r":["2701"],"t":{"allObject":{}}},"TkID0h":{"q":"TkID0h","w":2705,"e":"173,60","r":["2705"],"t":{"allObject":{}}},"CLDU4s":{"q":"CLDU4s","w":2702,"e":"173,63","r":["2702"],"t":{"allObject":{}}},"K4T1cx":{"q":"K4T1cx","w":2701,"e":"173,66","r":["2701"],"t":{"allObject":{}}},"Vu42c9":{"q":"Vu42c9","w":2703,"e":"173,67","r":["2703"],"t":{"allObject":{}}},"cHpnq9":{"q":"cHpnq9","w":2704,"e":"173,68","r":["2704"],"t":{"allObject":{}}},"vbiPLX":{"q":"vbiPLX","w":2702,"e":"173,70","r":["2702"],"t":{"allObject":{}}},"d6Bt4P":{"q":"d6Bt4P","w":2703,"e":"173,71","r":["2703"],"t":{"allObject":{}}},"DClK8Q":{"q":"DClK8Q","w":2504,"e":"174,45","r":["2504"],"t":{"allObject":{}}},"viEGya":{"q":"viEGya","w":2705,"e":"174,46","r":["2705"],"t":{"allObject":{}}},"8F7Oqz":{"q":"8F7Oqz","w":2701,"e":"174,49","r":["2701"],"t":{"allObject":{}}},"Yi2GZY":{"q":"Yi2GZY","w":2702,"e":"174,50","r":["2702"],"t":{"allObject":{}}},"ROszGm":{"q":"ROszGm","w":2704,"e":"174,51","r":["2704"],"t":{"allObject":{}}},"V2fxgM":{"q":"V2fxgM","w":2702,"e":"174,56","r":["2702"],"t":{"allObject":{}}},"JtKpW3":{"q":"JtKpW3","w":2701,"e":"174,63","r":["2701"],"t":{"allObject":{}}},"6oL7DY":{"q":"6oL7DY","w":2705,"e":"174,64","r":["2705"],"t":{"allObject":{}}},"NrtgNC":{"q":"NrtgNC","w":2702,"e":"174,67","r":["2702"],"t":{"allObject":{}}},"K9WdFm":{"q":"K9WdFm","w":2701,"e":"174,70","r":["2701"],"t":{"allObject":{}}},"MEZD3f":{"q":"MEZD3f","w":2701,"e":"174,71","r":["2701"],"t":{"allObject":{}}},"8Dou36":{"q":"8Dou36","w":2501,"e":"175,45","r":["2501"],"t":{"allObject":{}}},"wuy9Lc":{"q":"wuy9Lc","w":2702,"e":"175,49","r":["2702"],"t":{"allObject":{}}},"bU6uCx":{"q":"bU6uCx","w":2701,"e":"175,50","r":["2701"],"t":{"allObject":{}}},"ClrKej":{"q":"ClrKej","w":2702,"e":"175,53","r":["2702"],"t":{"allObject":{}}},"NfJeP0":{"q":"NfJeP0","w":2702,"e":"175,54","r":["2702"],"t":{"allObject":{}}},"pzhg00":{"q":"pzhg00","w":2704,"e":"175,55","r":["2704"],"t":{"allObject":{}}},"u3aoD3":{"q":"u3aoD3","w":2701,"e":"175,57","r":["2701"],"t":{"allObject":{}}},"1LhJmI":{"q":"1LhJmI","w":2703,"e":"175,58","r":["2703"],"t":{"allObject":{}}},"44ko2A":{"q":"44ko2A","w":2702,"e":"175,59","r":["2702"],"t":{"allObject":{}}},"Ajz3OG":{"q":"Ajz3OG","w":2702,"e":"175,63","r":["2702"],"t":{"allObject":{}}},"h0VuMp":{"q":"h0VuMp","w":2703,"e":"175,67","r":["2703"],"t":{"allObject":{}}},"YOU70e":{"q":"YOU70e","w":2701,"e":"175,68","r":["2701"],"t":{"allObject":{}}},"AbyaqP":{"q":"AbyaqP","w":2702,"e":"175,69","r":["2702"],"t":{"allObject":{}}},"QIbOoJ":{"q":"QIbOoJ","w":2703,"e":"175,70","r":["2703"],"t":{"allObject":{}}},"KQ3ytZ":{"q":"KQ3ytZ","w":2702,"e":"175,71","r":["2702"],"t":{"allObject":{}}},"HfxC4F":{"q":"HfxC4F","w":3001,"e":"175,190","r":["3001"],"t":{"allObject":{}}},"yX4UAk":{"q":"yX4UAk","w":2502,"e":"176,44","r":["2502"],"t":{"allObject":{}}},"Q84GNR":{"q":"Q84GNR","w":2702,"e":"176,45","r":["2702"],"t":{"allObject":{}}},"gpHp2Q":{"q":"gpHp2Q","w":2704,"e":"176,49","r":["2704"],"t":{"allObject":{}}},"wuqUGN":{"q":"wuqUGN","w":2703,"e":"176,51","r":["2703"],"t":{"allObject":{}}},"jafbjC":{"q":"jafbjC","w":2702,"e":"176,52","r":["2702"],"t":{"allObject":{}}},"ln4LYU":{"q":"ln4LYU","w":2701,"e":"176,53","r":["2701"],"t":{"allObject":{}}},"J58UOs":{"q":"J58UOs","w":2701,"e":"176,54","r":["2701"],"t":{"allObject":{}}},"VEdn16":{"q":"VEdn16","w":2705,"e":"176,57","r":["2705"],"t":{"allObject":{}}},"Rjvz5V":{"q":"Rjvz5V","w":2702,"e":"176,60","r":["2702"],"t":{"allObject":{}}},"vMUyMa":{"q":"vMUyMa","w":2704,"e":"176,61","r":["2704"],"t":{"allObject":{}}},"TDKiya":{"q":"TDKiya","w":2703,"e":"176,63","r":["2703"],"t":{"allObject":{}}},"AVtPZ8":{"q":"AVtPZ8","w":2705,"e":"176,67","r":["2705"],"t":{"allObject":{}}},"ECNnzS":{"q":"ECNnzS","w":2702,"e":"176,70","r":["2702"],"t":{"allObject":{}}},"c3zkzQ":{"q":"c3zkzQ","w":2701,"e":"176,71","r":["2701"],"t":{"allObject":{}}},"p94iyh":{"q":"p94iyh","w":2503,"e":"177,43","r":["2503"],"t":{"allObject":{}}},"QxyVW6":{"q":"QxyVW6","w":2705,"e":"177,44","r":["2705"],"t":{"allObject":{}}},"XnuEgt":{"q":"XnuEgt","w":2703,"e":"177,47","r":["2703"],"t":{"allObject":{}}},"w5Vnjp":{"q":"w5Vnjp","w":2702,"e":"177,48","r":["2702"],"t":{"allObject":{}}},"99h5zu":{"q":"99h5zu","w":2703,"e":"177,51","r":["2703"],"t":{"allObject":{}}},"2VrJ9u":{"q":"2VrJ9u","w":2704,"e":"177,52","r":["2704"],"t":{"allObject":{}}},"kd1nOo":{"q":"kd1nOo","w":2702,"e":"177,54","r":["2702"],"t":{"allObject":{}}},"ehZet5":{"q":"ehZet5","w":2702,"e":"177,55","r":["2702"],"t":{"allObject":{}}},"gzGGJn":{"q":"gzGGJn","w":2702,"e":"177,56","r":["2702"],"t":{"allObject":{}}},"fxLZoi":{"q":"fxLZoi","w":2703,"e":"177,60","r":["2703"],"t":{"allObject":{}}},"QYW9yh":{"q":"QYW9yh","w":2702,"e":"177,63","r":["2702"],"t":{"allObject":{}}},"eR1QXW":{"q":"eR1QXW","w":2703,"e":"177,64","r":["2703"],"t":{"allObject":{}}},"ffcbVQ":{"q":"ffcbVQ","w":2704,"e":"177,65","r":["2704"],"t":{"allObject":{}}},"JyrxJ0":{"q":"JyrxJ0","w":2703,"e":"177,70","r":["2703"],"t":{"allObject":{}}},"LdUgdF":{"q":"LdUgdF","w":2701,"e":"177,71","r":["2701"],"t":{"allObject":{}}},"GBRZbR":{"q":"GBRZbR","w":2504,"e":"178,43","r":["2504"],"t":{"allObject":{}}},"irAgQq":{"q":"irAgQq","w":2705,"e":"178,47","r":["2705"],"t":{"allObject":{}}},"TgNDaf":{"q":"TgNDaf","w":2702,"e":"178,50","r":["2702"],"t":{"allObject":{}}},"E1BKRR":{"q":"E1BKRR","w":2701,"e":"178,51","r":["2701"],"t":{"allObject":{}}},"RJmWj4":{"q":"RJmWj4","w":2701,"e":"178,54","r":["2701"],"t":{"allObject":{}}},"pbqfc8":{"q":"pbqfc8","w":2702,"e":"178,55","r":["2702"],"t":{"allObject":{}}},"8XmlH4":{"q":"8XmlH4","w":2703,"e":"178,56","r":["2703"],"t":{"allObject":{}}},"1dtRjs":{"q":"1dtRjs","w":2705,"e":"178,60","r":["2705"],"t":{"allObject":{}}},"sYWesv":{"q":"sYWesv","w":2702,"e":"178,63","r":["2702"],"t":{"allObject":{}}},"m8XQJi":{"q":"m8XQJi","w":2701,"e":"178,64","r":["2701"],"t":{"allObject":{}}},"GubJYF":{"q":"GubJYF","w":2701,"e":"178,70","r":["2701"],"t":{"allObject":{}}},"0q4wHJ":{"q":"0q4wHJ","w":2701,"e":"178,71","r":["2701"],"t":{"allObject":{}}},"bXatqq":{"q":"bXatqq","w":2503,"e":"179,42","r":["2503"],"t":{"allObject":{}}},"o0pFqa":{"q":"o0pFqa","w":2703,"e":"179,43","r":["2703"],"t":{"allObject":{}}},"2UDgbb":{"q":"2UDgbb","w":2701,"e":"179,50","r":["2701"],"t":{"allObject":{}}},"d8TKrz":{"q":"d8TKrz","w":2703,"e":"179,51","r":["2703"],"t":{"allObject":{}}},"YpiKTH":{"q":"YpiKTH","w":2701,"e":"179,52","r":["2701"],"t":{"allObject":{}}},"lP1chJ":{"q":"lP1chJ","w":2705,"e":"179,53","r":["2705"],"t":{"allObject":{}}},"SXi5wJ":{"q":"SXi5wJ","w":2704,"e":"179,56","r":["2704"],"t":{"allObject":{}}},"8QYDM9":{"q":"8QYDM9","w":2704,"e":"179,58","r":["2704"],"t":{"allObject":{}}},"WCdYmK":{"q":"WCdYmK","w":2705,"e":"179,63","r":["2705"],"t":{"allObject":{}}},"Dy11M1":{"q":"Dy11M1","w":2702,"e":"179,66","r":["2702"],"t":{"allObject":{}}},"4K6ZyJ":{"q":"4K6ZyJ","w":2701,"e":"179,67","r":["2701"],"t":{"allObject":{}}},"xYw6er":{"q":"xYw6er","w":2704,"e":"179,68","r":["2704"],"t":{"allObject":{}}},"HlubXr":{"q":"HlubXr","w":2703,"e":"179,70","r":["2703"],"t":{"allObject":{}}},"f4AoJz":{"q":"f4AoJz","w":2702,"e":"179,71","r":["2702"],"t":{"allObject":{}}},"ddXooP":{"q":"ddXooP","w":2504,"e":"180,41","r":["2504"],"t":{"allObject":{}}},"MX6kQP":{"q":"MX6kQP","w":2705,"e":"180,42","r":["2705"],"t":{"allObject":{}}},"CgyneZ":{"q":"CgyneZ","w":2703,"e":"180,45","r":["2703"],"t":{"allObject":{}}},"iY3P1U":{"q":"iY3P1U","w":2701,"e":"180,46","r":["2701"],"t":{"allObject":{}}},"cNSBFy":{"q":"cNSBFy","w":2704,"e":"180,50","r":["2704"],"t":{"allObject":{}}},"jXWDk3":{"q":"jXWDk3","w":2703,"e":"180,52","r":["2703"],"t":{"allObject":{}}},"7SiKyI":{"q":"7SiKyI","w":2704,"e":"180,66","r":["2704"],"t":{"allObject":{}}},"iokVej":{"q":"iokVej","w":2704,"e":"180,70","r":["2704"],"t":{"allObject":{}}},"8nw1WA":{"q":"8nw1WA","w":2503,"e":"181,41","r":["2503"],"t":{"allObject":{}}},"1rvFbP":{"q":"1rvFbP","w":2704,"e":"181,45","r":["2704"],"t":{"allObject":{}}},"8EIMQj":{"q":"8EIMQj","w":2701,"e":"181,47","r":["2701"],"t":{"allObject":{}}},"OO7d3J":{"q":"OO7d3J","w":2704,"e":"181,48","r":["2704"],"t":{"allObject":{}}},"vHpxsK":{"q":"vHpxsK","w":2701,"e":"181,52","r":["2701"],"t":{"allObject":{}}},"NM7yqN":{"q":"NM7yqN","w":2705,"e":"181,56","r":["2705"],"t":{"allObject":{}}},"TmZ1CG":{"q":"TmZ1CG","w":2701,"e":"181,59","r":["2701"],"t":{"allObject":{}}},"UlNBXr":{"q":"UlNBXr","w":2704,"e":"181,60","r":["2704"],"t":{"allObject":{}}},"QIiWFZ":{"q":"QIiWFZ","w":2702,"e":"181,62","r":["2702"],"t":{"allObject":{}}},"zX7ATc":{"q":"zX7ATc","w":2702,"e":"181,68","r":["2702"],"t":{"allObject":{}}},"aU2ymB":{"q":"aU2ymB","w":2701,"e":"181,69","r":["2701"],"t":{"allObject":{}}},"FwdzCS":{"q":"FwdzCS","w":2501,"e":"182,40","r":["2501"],"t":{"allObject":{}}},"VKbluP":{"q":"VKbluP","w":2701,"e":"182,41","r":["2701"],"t":{"allObject":{}}},"3M6Uxt":{"q":"3M6Uxt","w":2703,"e":"182,47","r":["2703"],"t":{"allObject":{}}},"zVSdvY":{"q":"zVSdvY","w":2702,"e":"182,50","r":["2702"],"t":{"allObject":{}}},"w5coJG":{"q":"w5coJG","w":2702,"e":"182,51","r":["2702"],"t":{"allObject":{}}},"Vs4QP3":{"q":"Vs4QP3","w":2701,"e":"182,52","r":["2701"],"t":{"allObject":{}}},"2JvVh6":{"q":"2JvVh6","w":2703,"e":"182,53","r":["2703"],"t":{"allObject":{}}},"uQnvKg":{"q":"uQnvKg","w":2702,"e":"182,54","r":["2702"],"t":{"allObject":{}}},"1rVBce":{"q":"1rVBce","w":2703,"e":"182,55","r":["2703"],"t":{"allObject":{}}},"DahuKq":{"q":"DahuKq","w":2703,"e":"182,59","r":["2703"],"t":{"allObject":{}}},"qnWoC6":{"q":"qnWoC6","w":2702,"e":"182,62","r":["2702"],"t":{"allObject":{}}},"J3HEHr":{"q":"J3HEHr","w":2704,"e":"182,63","r":["2704"],"t":{"allObject":{}}},"kVkJUv":{"q":"kVkJUv","w":2703,"e":"182,65","r":["2703"],"t":{"allObject":{}}},"KhdUkv":{"q":"KhdUkv","w":2703,"e":"182,66","r":["2703"],"t":{"allObject":{}}},"30mwnp":{"q":"30mwnp","w":2701,"e":"182,67","r":["2701"],"t":{"allObject":{}}},"FX0C72":{"q":"FX0C72","w":2704,"e":"182,68","r":["2704"],"t":{"allObject":{}}},"58g4uM":{"q":"58g4uM","w":2702,"e":"182,70","r":["2702"],"t":{"allObject":{}}},"MbG4hM":{"q":"MbG4hM","w":2702,"e":"182,71","r":["2702"],"t":{"allObject":{}}},"x7r3Hd":{"q":"x7r3Hd","w":2502,"e":"183,40","r":["2502"],"t":{"allObject":{}}},"nZUHhV":{"q":"nZUHhV","w":2703,"e":"183,41","r":["2703"],"t":{"allObject":{}}},"YnTjm5":{"q":"YnTjm5","w":2701,"e":"183,42","r":["2701"],"t":{"allObject":{}}},"tCq1VO":{"q":"tCq1VO","w":2703,"e":"183,43","r":["2703"],"t":{"allObject":{}}},"INPFk5":{"q":"INPFk5","w":2702,"e":"183,44","r":["2702"],"t":{"allObject":{}}},"i0Zqk2":{"q":"i0Zqk2","w":2702,"e":"183,45","r":["2702"],"t":{"allObject":{}}},"YXYBid":{"q":"YXYBid","w":2701,"e":"183,46","r":["2701"],"t":{"allObject":{}}},"xgLLbk":{"q":"xgLLbk","w":2705,"e":"183,47","r":["2705"],"t":{"allObject":{}}},"Xl9ZNX":{"q":"Xl9ZNX","w":2703,"e":"183,50","r":["2703"],"t":{"allObject":{}}},"94aCx1":{"q":"94aCx1","w":2704,"e":"183,51","r":["2704"],"t":{"allObject":{}}},"easDlj":{"q":"easDlj","w":2705,"e":"183,53","r":["2705"],"t":{"allObject":{}}},"EhIDat":{"q":"EhIDat","w":2705,"e":"183,59","r":["2705"],"t":{"allObject":{}}},"mUbbUk":{"q":"mUbbUk","w":2702,"e":"183,62","r":["2702"],"t":{"allObject":{}}},"1mae49":{"q":"1mae49","w":2702,"e":"183,65","r":["2702"],"t":{"allObject":{}}},"6Fa0wb":{"q":"6Fa0wb","w":2703,"e":"183,66","r":["2703"],"t":{"allObject":{}}},"KxpG58":{"q":"KxpG58","w":2703,"e":"183,67","r":["2703"],"t":{"allObject":{}}},"Wo7sHI":{"q":"Wo7sHI","w":2703,"e":"183,70","r":["2703"],"t":{"allObject":{}}},"pIOrtL":{"q":"pIOrtL","w":2702,"e":"183,71","r":["2702"],"t":{"allObject":{}}},"uSb3t6":{"q":"uSb3t6","w":2503,"e":"184,40","r":["2503"],"t":{"allObject":{}}},"JQkfJt":{"q":"JQkfJt","w":2704,"e":"184,41","r":["2704"],"t":{"allObject":{}}},"YRGX5m":{"q":"YRGX5m","w":2701,"e":"184,43","r":["2701"],"t":{"allObject":{}}},"6aD1vi":{"q":"6aD1vi","w":2703,"e":"184,44","r":["2703"],"t":{"allObject":{}}},"cGar3c":{"q":"cGar3c","w":2703,"e":"184,45","r":["2703"],"t":{"allObject":{}}},"1elLeH":{"q":"1elLeH","w":2701,"e":"184,46","r":["2701"],"t":{"allObject":{}}},"0MHg94":{"q":"0MHg94","w":2703,"e":"184,50","r":["2703"],"t":{"allObject":{}}},"HBLwuD":{"q":"HBLwuD","w":2701,"e":"184,56","r":["2701"],"t":{"allObject":{}}},"4GFLo5":{"q":"4GFLo5","w":2702,"e":"184,57","r":["2702"],"t":{"allObject":{}}},"YjMJIH":{"q":"YjMJIH","w":2703,"e":"184,58","r":["2703"],"t":{"allObject":{}}},"XvI7bn":{"q":"XvI7bn","w":2705,"e":"184,62","r":["2705"],"t":{"allObject":{}}},"cba9Cy":{"q":"cba9Cy","w":2704,"e":"184,65","r":["2704"],"t":{"allObject":{}}},"pJdLaN":{"q":"pJdLaN","w":2702,"e":"184,67","r":["2702"],"t":{"allObject":{}}},"HZlNag":{"q":"HZlNag","w":2703,"e":"184,68","r":["2703"],"t":{"allObject":{}}},"ii4nFv":{"q":"ii4nFv","w":2702,"e":"184,69","r":["2702"],"t":{"allObject":{}}},"1zLQZS":{"q":"1zLQZS","w":2704,"e":"184,70","r":["2704"],"t":{"allObject":{}}},"vZatjz":{"q":"vZatjz","w":2501,"e":"185,39","r":["2501"],"t":{"allObject":{}}},"s54llK":{"q":"s54llK","w":2702,"e":"185,40","r":["2702"],"t":{"allObject":{}}},"LvYQQb":{"q":"LvYQQb","w":2702,"e":"185,43","r":["2702"],"t":{"allObject":{}}},"i7DrNH":{"q":"i7DrNH","w":2705,"e":"185,44","r":["2705"],"t":{"allObject":{}}},"57pnOd":{"q":"57pnOd","w":2703,"e":"185,50","r":["2703"],"t":{"allObject":{}}},"Dp7quK":{"q":"Dp7quK","w":2703,"e":"185,51","r":["2703"],"t":{"allObject":{}}},"ncf0vh":{"q":"ncf0vh","w":2702,"e":"185,52","r":["2702"],"t":{"allObject":{}}},"cmmsuq":{"q":"cmmsuq","w":2705,"e":"185,56","r":["2705"],"t":{"allObject":{}}},"j1lteB":{"q":"j1lteB","w":2705,"e":"185,67","r":["2705"],"t":{"allObject":{}}},"0L5Xpz":{"q":"0L5Xpz","w":2705,"e":"185,72","r":["2705"],"t":{"allObject":{}}},"PvvKyO":{"q":"PvvKyO","w":2502,"e":"185,75","r":["2502"],"t":{"allObject":{}}},"C2HbSH":{"q":"C2HbSH","w":2502,"e":"186,39","r":["2502"],"t":{"allObject":{}}},"AoPuko":{"q":"AoPuko","w":2705,"e":"186,40","r":["2705"],"t":{"allObject":{}}},"qLqPOK":{"q":"qLqPOK","w":2702,"e":"186,43","r":["2702"],"t":{"allObject":{}}},"4kIpwF":{"q":"4kIpwF","w":2702,"e":"186,47","r":["2702"],"t":{"allObject":{}}},"BrS4mQ":{"q":"BrS4mQ","w":2703,"e":"186,48","r":["2703"],"t":{"allObject":{}}},"4tXjJg":{"q":"4tXjJg","w":2704,"e":"186,49","r":["2704"],"t":{"allObject":{}}},"S4grX5":{"q":"S4grX5","w":2701,"e":"186,51","r":["2701"],"t":{"allObject":{}}},"FesC4J":{"q":"FesC4J","w":2702,"e":"186,52","r":["2702"],"t":{"allObject":{}}},"ZQgtBb":{"q":"ZQgtBb","w":2701,"e":"186,53","r":["2701"],"t":{"allObject":{}}},"WcqWql":{"q":"WcqWql","w":2702,"e":"186,54","r":["2702"],"t":{"allObject":{}}},"RJlPfF":{"q":"RJlPfF","w":2702,"e":"186,55","r":["2702"],"t":{"allObject":{}}},"GxEc9G":{"q":"GxEc9G","w":2702,"e":"186,59","r":["2702"],"t":{"allObject":{}}},"fMBFC0":{"q":"fMBFC0","w":2702,"e":"186,60","r":["2702"],"t":{"allObject":{}}},"dWp6am":{"q":"dWp6am","w":2701,"e":"186,61","r":["2701"],"t":{"allObject":{}}},"CMUiht":{"q":"CMUiht","w":2703,"e":"186,65","r":["2703"],"t":{"allObject":{}}},"GPr6qT":{"q":"GPr6qT","w":2702,"e":"186,66","r":["2702"],"t":{"allObject":{}}},"STmBIP":{"q":"STmBIP","w":2702,"e":"186,70","r":["2702"],"t":{"allObject":{}}},"GiEM19":{"q":"GiEM19","w":2703,"e":"186,71","r":["2703"],"t":{"allObject":{}}},"qnqwMN":{"q":"qnqwMN","w":2501,"e":"186,75","r":["2501"],"t":{"allObject":{}}},"OOh3nF":{"q":"OOh3nF","w":2104,"e":"186,131","r":["210101"],"t":{"allObject":{}}},"IjYiun":{"q":"IjYiun","w":2108,"e":"186,132","r":["210101"],"t":{"allObject":{}}},"ck0LWK":{"q":"ck0LWK","w":2106,"e":"186,133","r":["210101"],"t":{"allObject":{}}},"PH5MjE":{"q":"PH5MjE","w":2502,"e":"187,39","r":["2502"],"t":{"allObject":{}}},"b6oOI1":{"q":"b6oOI1","w":2702,"e":"187,43","r":["2702"],"t":{"allObject":{}}},"TbzTbL":{"q":"TbzTbL","w":2701,"e":"187,47","r":["2701"],"t":{"allObject":{}}},"MLHsHq":{"q":"MLHsHq","w":2702,"e":"187,48","r":["2702"],"t":{"allObject":{}}},"TkWFfO":{"q":"TkWFfO","w":2703,"e":"187,51","r":["2703"],"t":{"allObject":{}}},"9IbOKP":{"q":"9IbOKP","w":2705,"e":"187,52","r":["2705"],"t":{"allObject":{}}},"tlwdY3":{"q":"tlwdY3","w":2702,"e":"187,55","r":["2702"],"t":{"allObject":{}}},"g0pGez":{"q":"g0pGez","w":2705,"e":"187,59","r":["2705"],"t":{"allObject":{}}},"Yk5j4l":{"q":"Yk5j4l","w":2704,"e":"187,62","r":["2704"],"t":{"allObject":{}}},"WoQrC0":{"q":"WoQrC0","w":2705,"e":"187,64","r":["2705"],"t":{"allObject":{}}},"WaKqP0":{"q":"WaKqP0","w":2702,"e":"187,70","r":["2702"],"t":{"allObject":{}}},"R6yaaT":{"q":"R6yaaT","w":2702,"e":"187,71","r":["2702"],"t":{"allObject":{}}},"1vFB8J":{"q":"1vFB8J","w":2501,"e":"187,75","r":["2501"],"t":{"allObject":{}}},"21GKO7":{"q":"21GKO7","w":2101,"e":"187,132","r":["210101"],"t":{"allObject":{}}},"GKGTIz":{"q":"GKGTIz","w":2108,"e":"187,134","r":["210101"],"t":{"allObject":{}}},"PWBesy":{"q":"PWBesy","w":2504,"e":"188,38","r":["2504"],"t":{"allObject":{}}},"sGmaAi":{"q":"sGmaAi","w":2703,"e":"188,39","r":["2703"],"t":{"allObject":{}}},"GtIm1U":{"q":"GtIm1U","w":2702,"e":"188,43","r":["2702"],"t":{"allObject":{}}},"tgazsy":{"q":"tgazsy","w":2703,"e":"188,44","r":["2703"],"t":{"allObject":{}}},"xxeXS2":{"q":"xxeXS2","w":2701,"e":"188,45","r":["2701"],"t":{"allObject":{}}},"x9ncqo":{"q":"x9ncqo","w":2704,"e":"188,46","r":["2704"],"t":{"allObject":{}}},"kNSlvl":{"q":"kNSlvl","w":2702,"e":"188,48","r":["2702"],"t":{"allObject":{}}},"qKhjRf":{"q":"qKhjRf","w":2701,"e":"188,49","r":["2701"],"t":{"allObject":{}}},"mMwIpr":{"q":"mMwIpr","w":2703,"e":"188,50","r":["2703"],"t":{"allObject":{}}},"OMM2k2":{"q":"OMM2k2","w":2702,"e":"188,51","r":["2702"],"t":{"allObject":{}}},"RJE9mS":{"q":"RJE9mS","w":2701,"e":"188,55","r":["2701"],"t":{"allObject":{}}},"zeToIw":{"q":"zeToIw","w":2701,"e":"188,56","r":["2701"],"t":{"allObject":{}}},"6v22ZX":{"q":"6v22ZX","w":2702,"e":"188,57","r":["2702"],"t":{"allObject":{}}},"1Rjnyv":{"q":"1Rjnyv","w":2701,"e":"188,58","r":["2701"],"t":{"allObject":{}}},"MfNXfQ":{"q":"MfNXfQ","w":2704,"e":"188,67","r":["2704"],"t":{"allObject":{}}},"PmkXhu":{"q":"PmkXhu","w":2702,"e":"188,69","r":["2702"],"t":{"allObject":{}}},"hwwr8s":{"q":"hwwr8s","w":2705,"e":"188,70","r":["2705"],"t":{"allObject":{}}},"pKKQDb":{"q":"pKKQDb","w":2702,"e":"188,73","r":["2702"],"t":{"allObject":{}}},"sKYTWf":{"q":"sKYTWf","w":2703,"e":"188,74","r":["2703"],"t":{"allObject":{}}},"AGxJoD":{"q":"AGxJoD","w":2502,"e":"188,75","r":["2502"],"t":{"allObject":{}}},"vNmRML":{"q":"vNmRML","w":2108,"e":"188,131","r":["210101"],"t":{"allObject":{}}},"xsICS3":{"q":"xsICS3","w":2103,"e":"188,134","r":["210101"],"t":{"allObject":{}}},"4VUYHG":{"q":"4VUYHG","w":2504,"e":"189,38","r":["2504"],"t":{"allObject":{}}},"yMqszC":{"q":"yMqszC","w":2701,"e":"189,39","r":["2701"],"t":{"allObject":{}}},"5TnRPq":{"q":"5TnRPq","w":2702,"e":"189,40","r":["2702"],"t":{"allObject":{}}},"cM3Hjo":{"q":"cM3Hjo","w":2702,"e":"189,41","r":["2702"],"t":{"allObject":{}}},"cy20Js":{"q":"cy20Js","w":2704,"e":"189,42","r":["2704"],"t":{"allObject":{}}},"hHYFSh":{"q":"hHYFSh","w":2704,"e":"189,44","r":["2704"],"t":{"allObject":{}}},"uT9ucP":{"q":"uT9ucP","w":2701,"e":"189,48","r":["2701"],"t":{"allObject":{}}},"cShrOX":{"q":"cShrOX","w":2702,"e":"189,49","r":["2702"],"t":{"allObject":{}}},"rjwjav":{"q":"rjwjav","w":2701,"e":"189,50","r":["2701"],"t":{"allObject":{}}},"0fhiZx":{"q":"0fhiZx","w":2702,"e":"189,51","r":["2702"],"t":{"allObject":{}}},"VyOm6r":{"q":"VyOm6r","w":2704,"e":"189,55","r":["2704"],"t":{"allObject":{}}},"Jk4OuY":{"q":"Jk4OuY","w":2704,"e":"189,57","r":["2704"],"t":{"allObject":{}}},"eHfzty":{"q":"eHfzty","w":2703,"e":"189,62","r":["2703"],"t":{"allObject":{}}},"4LBiya":{"q":"4LBiya","w":2703,"e":"189,63","r":["2703"],"t":{"allObject":{}}},"A0hLGi":{"q":"A0hLGi","w":2701,"e":"189,69","r":["2701"],"t":{"allObject":{}}},"00xGPH":{"q":"00xGPH","w":2704,"e":"189,73","r":["2704"],"t":{"allObject":{}}},"Q6HDDw":{"q":"Q6HDDw","w":2501,"e":"189,75","r":["2501"],"t":{"allObject":{}}},"wCPVGX":{"q":"wCPVGX","w":2107,"e":"189,131","r":["210101"],"t":{"allObject":{}}},"OHPPgW":{"q":"OHPPgW","w":2502,"e":"190,38","r":["2502"],"t":{"allObject":{}}},"VnQoh7":{"q":"VnQoh7","w":2703,"e":"190,39","r":["2703"],"t":{"allObject":{}}},"b9eCOi":{"q":"b9eCOi","w":2704,"e":"190,40","r":["2704"],"t":{"allObject":{}}},"XGYBlo":{"q":"XGYBlo","w":2703,"e":"190,46","r":["2703"],"t":{"allObject":{}}},"JjU7UA":{"q":"JjU7UA","w":2702,"e":"190,47","r":["2702"],"t":{"allObject":{}}},"qncCP0":{"q":"qncCP0","w":2705,"e":"190,48","r":["2705"],"t":{"allObject":{}}},"N1Cz2X":{"q":"N1Cz2X","w":2701,"e":"190,51","r":["2701"],"t":{"allObject":{}}},"HeJZMG":{"q":"HeJZMG","w":2701,"e":"190,52","r":["2701"],"t":{"allObject":{}}},"9YDsWQ":{"q":"9YDsWQ","w":2704,"e":"190,53","r":["2704"],"t":{"allObject":{}}},"Gcia48":{"q":"Gcia48","w":2703,"e":"190,59","r":["2703"],"t":{"allObject":{}}},"6ql1I2":{"q":"6ql1I2","w":2704,"e":"190,60","r":["2704"],"t":{"allObject":{}}},"Swnr7L":{"q":"Swnr7L","w":2705,"e":"190,62","r":["2705"],"t":{"allObject":{}}},"DaVcOJ":{"q":"DaVcOJ","w":2702,"e":"190,65","r":["2702"],"t":{"allObject":{}}},"K7K28Q":{"q":"K7K28Q","w":2705,"e":"190,66","r":["2705"],"t":{"allObject":{}}},"8mvcUN":{"q":"8mvcUN","w":2702,"e":"190,69","r":["2702"],"t":{"allObject":{}}},"wn7Bnw":{"q":"wn7Bnw","w":2502,"e":"190,75","r":["2502"],"t":{"allObject":{}}},"dNXMO8":{"q":"dNXMO8","w":2107,"e":"190,131","r":["210101"],"t":{"allObject":{}}},"qyP4Mw":{"q":"qyP4Mw","w":2107,"e":"190,132","r":["210101"],"t":{"allObject":{}}},"grdJL7":{"q":"grdJL7","w":2106,"e":"190,133","r":["210101"],"t":{"allObject":{}}},"hRek3L":{"q":"hRek3L","w":2503,"e":"191,37","r":["2503"],"t":{"allObject":{}}},"YMCMWO":{"q":"YMCMWO","w":2704,"e":"191,38","r":["2704"],"t":{"allObject":{}}},"Vnc5Ox":{"q":"Vnc5Ox","w":2701,"e":"191,42","r":["2701"],"t":{"allObject":{}}},"73nXww":{"q":"73nXww","w":2705,"e":"191,43","r":["2705"],"t":{"allObject":{}}},"2TMXIf":{"q":"2TMXIf","w":2701,"e":"191,46","r":["2701"],"t":{"allObject":{}}},"vSy0kc":{"q":"vSy0kc","w":2701,"e":"191,47","r":["2701"],"t":{"allObject":{}}},"05uWXl":{"q":"05uWXl","w":2702,"e":"191,51","r":["2702"],"t":{"allObject":{}}},"dQtWua":{"q":"dQtWua","w":2703,"e":"191,52","r":["2703"],"t":{"allObject":{}}},"hzX2Xq":{"q":"hzX2Xq","w":2702,"e":"191,55","r":["2702"],"t":{"allObject":{}}},"ICdQ1b":{"q":"ICdQ1b","w":2701,"e":"191,56","r":["2701"],"t":{"allObject":{}}},"3xLkd1":{"q":"3xLkd1","w":2705,"e":"191,57","r":["2705"],"t":{"allObject":{}}},"dVUQ5G":{"q":"dVUQ5G","w":2702,"e":"191,65","r":["2702"],"t":{"allObject":{}}},"G5oUlq":{"q":"G5oUlq","w":2704,"e":"191,69","r":["2704"],"t":{"allObject":{}}},"81ingB":{"q":"81ingB","w":2704,"e":"191,71","r":["2704"],"t":{"allObject":{}}},"Z51Y3V":{"q":"Z51Y3V","w":2702,"e":"191,73","r":["2702"],"t":{"allObject":{}}},"O9TlOp":{"q":"O9TlOp","w":2702,"e":"191,74","r":["2702"],"t":{"allObject":{}}},"M5BgNA":{"q":"M5BgNA","w":2504,"e":"191,75","r":["2504"],"t":{"allObject":{}}},"rhmUfq":{"q":"rhmUfq","w":2503,"e":"192,37","r":["2503"],"t":{"allObject":{}}},"2WdSR0":{"q":"2WdSR0","w":2705,"e":"192,40","r":["2705"],"t":{"allObject":{}}},"HTU6Nl":{"q":"HTU6Nl","w":2701,"e":"192,46","r":["2701"],"t":{"allObject":{}}},"0utx27":{"q":"0utx27","w":2702,"e":"192,47","r":["2702"],"t":{"allObject":{}}},"Pyc9kn":{"q":"Pyc9kn","w":2705,"e":"192,51","r":["2705"],"t":{"allObject":{}}},"ELwBX9":{"q":"ELwBX9","w":2705,"e":"192,54","r":["2705"],"t":{"allObject":{}}},"oDJqF1":{"q":"oDJqF1","w":2701,"e":"192,60","r":["2701"],"t":{"allObject":{}}},"z85TeT":{"q":"z85TeT","w":2702,"e":"192,61","r":["2702"],"t":{"allObject":{}}},"rtyhg3":{"q":"rtyhg3","w":2702,"e":"192,65","r":["2702"],"t":{"allObject":{}}},"hzb38O":{"q":"hzb38O","w":2704,"e":"192,73","r":["2704"],"t":{"allObject":{}}},"g4ZnOx":{"q":"g4ZnOx","w":2503,"e":"192,75","r":["2503"],"t":{"allObject":{}}},"o3zIBD":{"q":"o3zIBD","w":2501,"e":"193,37","r":["2501"],"t":{"allObject":{}}},"wpZfQ5":{"q":"wpZfQ5","w":2701,"e":"193,38","r":["2701"],"t":{"allObject":{}}},"WTRjyF":{"q":"WTRjyF","w":2703,"e":"193,39","r":["2703"],"t":{"allObject":{}}},"LBgpls":{"q":"LBgpls","w":2705,"e":"193,46","r":["2705"],"t":{"allObject":{}}},"ShHOvX":{"q":"ShHOvX","w":2701,"e":"193,49","r":["2701"],"t":{"allObject":{}}},"u6nAua":{"q":"u6nAua","w":2703,"e":"193,50","r":["2703"],"t":{"allObject":{}}},"CCUZFY":{"q":"CCUZFY","w":2705,"e":"193,60","r":["2705"],"t":{"allObject":{}}},"oWz424":{"q":"oWz424","w":2701,"e":"193,63","r":["2701"],"t":{"allObject":{}}},"T8BUuc":{"q":"T8BUuc","w":2703,"e":"193,64","r":["2703"],"t":{"allObject":{}}},"U0AI7k":{"q":"U0AI7k","w":2702,"e":"193,65","r":["2702"],"t":{"allObject":{}}},"7Lb9UY":{"q":"7Lb9UY","w":2704,"e":"193,66","r":["2704"],"t":{"allObject":{}}},"Y1irCP":{"q":"Y1irCP","w":2703,"e":"193,68","r":["2703"],"t":{"allObject":{}}},"U9PoQj":{"q":"U9PoQj","w":2705,"e":"193,69","r":["2705"],"t":{"allObject":{}}},"3KnVTn":{"q":"3KnVTn","w":2701,"e":"193,72","r":["2701"],"t":{"allObject":{}}},"7qNRTu":{"q":"7qNRTu","w":2504,"e":"193,75","r":["2504"],"t":{"allObject":{}}},"MFMMV6":{"q":"MFMMV6","w":2501,"e":"194,37","r":["2501"],"t":{"allObject":{}}},"Lp6fbQ":{"q":"Lp6fbQ","w":2703,"e":"194,38","r":["2703"],"t":{"allObject":{}}},"CsdFQo":{"q":"CsdFQo","w":2701,"e":"194,39","r":["2701"],"t":{"allObject":{}}},"si0tHg":{"q":"si0tHg","w":2703,"e":"194,43","r":["2703"],"t":{"allObject":{}}},"4aG9Ej":{"q":"4aG9Ej","w":2704,"e":"194,44","r":["2704"],"t":{"allObject":{}}},"kWvQRI":{"q":"kWvQRI","w":2703,"e":"194,49","r":["2703"],"t":{"allObject":{}}},"xksGHq":{"q":"xksGHq","w":2702,"e":"194,50","r":["2702"],"t":{"allObject":{}}},"xGrbWe":{"q":"xGrbWe","w":2704,"e":"194,57","r":["2704"],"t":{"allObject":{}}},"SzM1eu":{"q":"SzM1eu","w":2703,"e":"194,59","r":["2703"],"t":{"allObject":{}}},"i69cyv":{"q":"i69cyv","w":2703,"e":"194,63","r":["2703"],"t":{"allObject":{}}},"jXiG7c":{"q":"jXiG7c","w":2702,"e":"194,64","r":["2702"],"t":{"allObject":{}}},"FXiyrZ":{"q":"FXiyrZ","w":2703,"e":"194,65","r":["2703"],"t":{"allObject":{}}},"7BLozW":{"q":"7BLozW","w":2702,"e":"194,68","r":["2702"],"t":{"allObject":{}}},"AYpcvZ":{"q":"AYpcvZ","w":2701,"e":"194,72","r":["2701"],"t":{"allObject":{}}},"K1pJrI":{"q":"K1pJrI","w":2701,"e":"194,73","r":["2701"],"t":{"allObject":{}}},"P0Sni6":{"q":"P0Sni6","w":2702,"e":"194,74","r":["2702"],"t":{"allObject":{}}},"3uLkaj":{"q":"3uLkaj","w":2501,"e":"194,75","r":["2501"],"t":{"allObject":{}}},"5jHU4Y":{"q":"5jHU4Y","w":2207,"e":"194,151","r":["220101"],"t":{"allObject":{}}},"G9D7aq":{"q":"G9D7aq","w":2208,"e":"194,152","r":["220101"],"t":{"allObject":{}}},"D6iG8Y":{"q":"D6iG8Y","w":2208,"e":"194,153","r":["220101"],"t":{"allObject":{}}},"D71qCt":{"q":"D71qCt","w":2204,"e":"194,154","r":["220101"],"t":{"allObject":{}}},"OImVjF":{"q":"OImVjF","w":2503,"e":"195,37","r":["2503"],"t":{"allObject":{}}},"zey31Y":{"q":"zey31Y","w":2702,"e":"195,38","r":["2702"],"t":{"allObject":{}}},"RA8tEt":{"q":"RA8tEt","w":2703,"e":"195,39","r":["2703"],"t":{"allObject":{}}},"6DNcds":{"q":"6DNcds","w":2702,"e":"195,40","r":["2702"],"t":{"allObject":{}}},"NfoDyf":{"q":"NfoDyf","w":2704,"e":"195,41","r":["2704"],"t":{"allObject":{}}},"1tXc9c":{"q":"1tXc9c","w":2701,"e":"195,43","r":["2701"],"t":{"allObject":{}}},"H2L0FI":{"q":"H2L0FI","w":2705,"e":"195,49","r":["2705"],"t":{"allObject":{}}},"5ZTwSv":{"q":"5ZTwSv","w":2702,"e":"195,52","r":["2702"],"t":{"allObject":{}}},"Ik5VtP":{"q":"Ik5VtP","w":2704,"e":"195,53","r":["2704"],"t":{"allObject":{}}},"YVyF9E":{"q":"YVyF9E","w":2703,"e":"195,55","r":["2703"],"t":{"allObject":{}}},"gu73EC":{"q":"gu73EC","w":2702,"e":"195,56","r":["2702"],"t":{"allObject":{}}},"cKDDHA":{"q":"cKDDHA","w":2702,"e":"195,59","r":["2702"],"t":{"allObject":{}}},"S79J1L":{"q":"S79J1L","w":2705,"e":"195,63","r":["2705"],"t":{"allObject":{}}},"u7evTn":{"q":"u7evTn","w":2702,"e":"195,66","r":["2702"],"t":{"allObject":{}}},"lrQSjs":{"q":"lrQSjs","w":2702,"e":"195,67","r":["2702"],"t":{"allObject":{}}},"HW4JCj":{"q":"HW4JCj","w":2703,"e":"195,68","r":["2703"],"t":{"allObject":{}}},"SEKzj5":{"q":"SEKzj5","w":2704,"e":"195,72","r":["2704"],"t":{"allObject":{}}},"p6ezAo":{"q":"p6ezAo","w":2703,"e":"195,74","r":["2703"],"t":{"allObject":{}}},"AnyFjW":{"q":"AnyFjW","w":2502,"e":"195,75","r":["2502"],"t":{"allObject":{}}},"p2eOPp":{"q":"p2eOPp","w":2207,"e":"195,151","r":["220101"],"t":{"allObject":{}}},"Cpss7F":{"q":"Cpss7F","w":2201,"e":"195,152","r":["220101"],"t":{"allObject":{}}},"K6sLYn":{"q":"K6sLYn","w":2502,"e":"196,37","r":["2502"],"t":{"allObject":{}}},"WbHoFO":{"q":"WbHoFO","w":2701,"e":"196,38","r":["2701"],"t":{"allObject":{}}},"V0LeQ2":{"q":"V0LeQ2","w":2702,"e":"196,39","r":["2702"],"t":{"allObject":{}}},"YEX2jr":{"q":"YEX2jr","w":2702,"e":"196,40","r":["2702"],"t":{"allObject":{}}},"GE3lNU":{"q":"GE3lNU","w":2705,"e":"196,43","r":["2705"],"t":{"allObject":{}}},"L99GeH":{"q":"L99GeH","w":2701,"e":"196,46","r":["2701"],"t":{"allObject":{}}},"83zkD4":{"q":"83zkD4","w":2704,"e":"196,47","r":["2704"],"t":{"allObject":{}}},"cWgZcA":{"q":"cWgZcA","w":2701,"e":"196,52","r":["2701"],"t":{"allObject":{}}},"J4pzy5":{"q":"J4pzy5","w":2705,"e":"196,55","r":["2705"],"t":{"allObject":{}}},"4MGIRE":{"q":"4MGIRE","w":2705,"e":"196,58","r":["2705"],"t":{"allObject":{}}},"6ZMPHG":{"q":"6ZMPHG","w":2704,"e":"196,61","r":["2704"],"t":{"allObject":{}}},"AIuRyO":{"q":"AIuRyO","w":2704,"e":"196,66","r":["2704"],"t":{"allObject":{}}},"ON1wUh":{"q":"ON1wUh","w":2702,"e":"196,68","r":["2702"],"t":{"allObject":{}}},"m6Klwt":{"q":"m6Klwt","w":2702,"e":"196,69","r":["2702"],"t":{"allObject":{}}},"ipeTCR":{"q":"ipeTCR","w":2703,"e":"196,70","r":["2703"],"t":{"allObject":{}}},"Wmnjc3":{"q":"Wmnjc3","w":2702,"e":"196,71","r":["2702"],"t":{"allObject":{}}},"tdcMPf":{"q":"tdcMPf","w":2703,"e":"196,74","r":["2703"],"t":{"allObject":{}}},"gDNwsI":{"q":"gDNwsI","w":2504,"e":"196,75","r":["2504"],"t":{"allObject":{}}},"RwZpLO":{"q":"RwZpLO","w":2207,"e":"196,151","r":["220101"],"t":{"allObject":{}}},"cF25sj":{"q":"cF25sj","w":2207,"e":"196,154","r":["220101"],"t":{"allObject":{}}},"vYveEh":{"q":"vYveEh","w":2501,"e":"197,37","r":["2501"],"t":{"allObject":{}}},"Zwd88r":{"q":"Zwd88r","w":2705,"e":"197,38","r":["2705"],"t":{"allObject":{}}},"4MvfTH":{"q":"4MvfTH","w":2702,"e":"197,41","r":["2702"],"t":{"allObject":{}}},"UU8CQ4":{"q":"UU8CQ4","w":2702,"e":"197,42","r":["2702"],"t":{"allObject":{}}},"xeij6o":{"q":"xeij6o","w":2701,"e":"197,46","r":["2701"],"t":{"allObject":{}}},"WpWYfR":{"q":"WpWYfR","w":2701,"e":"197,52","r":["2701"],"t":{"allObject":{}}},"2SAlOP":{"q":"2SAlOP","w":2702,"e":"197,53","r":["2702"],"t":{"allObject":{}}},"tUtmh3":{"q":"tUtmh3","w":2701,"e":"197,54","r":["2701"],"t":{"allObject":{}}},"VOOsbt":{"q":"VOOsbt","w":2703,"e":"197,68","r":["2703"],"t":{"allObject":{}}},"lqT4la":{"q":"lqT4la","w":2704,"e":"197,69","r":["2704"],"t":{"allObject":{}}},"OduT6B":{"q":"OduT6B","w":2705,"e":"197,71","r":["2705"],"t":{"allObject":{}}},"wbvlc4":{"q":"wbvlc4","w":2702,"e":"197,74","r":["2702"],"t":{"allObject":{}}},"YN9b15":{"q":"YN9b15","w":2501,"e":"197,75","r":["2501"],"t":{"allObject":{}}},"N5vgXb":{"q":"N5vgXb","w":2207,"e":"197,151","r":["220101"],"t":{"allObject":{}}},"qqcuVD":{"q":"qqcuVD","w":2207,"e":"197,154","r":["220101"],"t":{"allObject":{}}},"09raay":{"q":"09raay","w":2504,"e":"198,37","r":["2504"],"t":{"allObject":{}}},"fqAIN2":{"q":"fqAIN2","w":2701,"e":"198,41","r":["2701"],"t":{"allObject":{}}},"UfVHuM":{"q":"UfVHuM","w":2702,"e":"198,42","r":["2702"],"t":{"allObject":{}}},"u5pAtb":{"q":"u5pAtb","w":2701,"e":"198,46","r":["2701"],"t":{"allObject":{}}},"brKzgy":{"q":"brKzgy","w":2703,"e":"198,47","r":["2703"],"t":{"allObject":{}}},"s6wpzb":{"q":"s6wpzb","w":2701,"e":"198,48","r":["2701"],"t":{"allObject":{}}},"MtbeAq":{"q":"MtbeAq","w":2704,"e":"198,49","r":["2704"],"t":{"allObject":{}}},"zKu5oj":{"q":"zKu5oj","w":2704,"e":"198,51","r":["2704"],"t":{"allObject":{}}},"qA4VQe":{"q":"qA4VQe","w":2703,"e":"198,53","r":["2703"],"t":{"allObject":{}}},"dnrjvU":{"q":"dnrjvU","w":2702,"e":"198,54","r":["2702"],"t":{"allObject":{}}},"F4vhye":{"q":"F4vhye","w":2701,"e":"198,61","r":["2701"],"t":{"allObject":{}}},"qu5omW":{"q":"qu5omW","w":2703,"e":"198,62","r":["2703"],"t":{"allObject":{}}},"sRxPqD":{"q":"sRxPqD","w":2702,"e":"198,63","r":["2702"],"t":{"allObject":{}}},"J46sLr":{"q":"J46sLr","w":2703,"e":"198,64","r":["2703"],"t":{"allObject":{}}},"dH6975":{"q":"dH6975","w":2701,"e":"198,65","r":["2701"],"t":{"allObject":{}}},"ZzljGJ":{"q":"ZzljGJ","w":2703,"e":"198,66","r":["2703"],"t":{"allObject":{}}},"gRvRtW":{"q":"gRvRtW","w":2701,"e":"198,67","r":["2701"],"t":{"allObject":{}}},"v3C2x7":{"q":"v3C2x7","w":2703,"e":"198,68","r":["2703"],"t":{"allObject":{}}},"lrBKM4":{"q":"lrBKM4","w":2701,"e":"198,74","r":["2701"],"t":{"allObject":{}}},"SdsLRJ":{"q":"SdsLRJ","w":2501,"e":"198,75","r":["2501"],"t":{"allObject":{}}},"iwa0GY":{"q":"iwa0GY","w":2208,"e":"198,151","r":["220101"],"t":{"allObject":{}}},"Z6mrtB":{"q":"Z6mrtB","w":2208,"e":"198,152","r":["220101"],"t":{"allObject":{}}},"MFM5nq":{"q":"MFM5nq","w":2207,"e":"198,153","r":["220101"],"t":{"allObject":{}}},"Ixt0Jr":{"q":"Ixt0Jr","w":2207,"e":"198,154","r":["220101"],"t":{"allObject":{}}},"uEXmyd":{"q":"uEXmyd","w":2501,"e":"199,37","r":["2501"],"t":{"allObject":{}}},"hCQuyE":{"q":"hCQuyE","w":2701,"e":"199,41","r":["2701"],"t":{"allObject":{}}},"wvfHom":{"q":"wvfHom","w":2703,"e":"199,42","r":["2703"],"t":{"allObject":{}}},"IG0Q2D":{"q":"IG0Q2D","w":2703,"e":"199,43","r":["2703"],"t":{"allObject":{}}},"tJbSAZ":{"q":"tJbSAZ","w":2701,"e":"199,44","r":["2701"],"t":{"allObject":{}}},"coAUeD":{"q":"coAUeD","w":2702,"e":"199,45","r":["2702"],"t":{"allObject":{}}},"crMDbO":{"q":"crMDbO","w":2703,"e":"199,46","r":["2703"],"t":{"allObject":{}}},"V4kVrE":{"q":"V4kVrE","w":2702,"e":"199,47","r":["2702"],"t":{"allObject":{}}},"v3Dg2E":{"q":"v3Dg2E","w":2703,"e":"199,48","r":["2703"],"t":{"allObject":{}}},"tuAOCH":{"q":"tuAOCH","w":2701,"e":"199,53","r":["2701"],"t":{"allObject":{}}},"ntSkx8":{"q":"ntSkx8","w":2702,"e":"199,54","r":["2702"],"t":{"allObject":{}}},"2XZwrT":{"q":"2XZwrT","w":2703,"e":"199,55","r":["2703"],"t":{"allObject":{}}},"q5w1f8":{"q":"q5w1f8","w":2701,"e":"199,56","r":["2701"],"t":{"allObject":{}}},"tIbcNL":{"q":"tIbcNL","w":2702,"e":"199,57","r":["2702"],"t":{"allObject":{}}},"IUjOd7":{"q":"IUjOd7","w":2702,"e":"199,58","r":["2702"],"t":{"allObject":{}}},"WfIANL":{"q":"WfIANL","w":2703,"e":"199,59","r":["2703"],"t":{"allObject":{}}},"8hPxyP":{"q":"8hPxyP","w":2701,"e":"199,60","r":["2701"],"t":{"allObject":{}}},"lXNIG8":{"q":"lXNIG8","w":2701,"e":"199,61","r":["2701"],"t":{"allObject":{}}},"af3DfG":{"q":"af3DfG","w":2701,"e":"199,62","r":["2701"],"t":{"allObject":{}}},"wRY3af":{"q":"wRY3af","w":2702,"e":"199,63","r":["2702"],"t":{"allObject":{}}},"JllBM1":{"q":"JllBM1","w":2701,"e":"199,64","r":["2701"],"t":{"allObject":{}}},"7HyP48":{"q":"7HyP48","w":2702,"e":"199,65","r":["2702"],"t":{"allObject":{}}},"nxdfRT":{"q":"nxdfRT","w":2701,"e":"199,66","r":["2701"],"t":{"allObject":{}}},"4Q2zo9":{"q":"4Q2zo9","w":2702,"e":"199,67","r":["2702"],"t":{"allObject":{}}},"Tm04lC":{"q":"Tm04lC","w":2702,"e":"199,68","r":["2702"],"t":{"allObject":{}}},"DTYytv":{"q":"DTYytv","w":2702,"e":"199,69","r":["2702"],"t":{"allObject":{}}},"wC5iA9":{"q":"wC5iA9","w":2701,"e":"199,70","r":["2701"],"t":{"allObject":{}}},"wwx5N4":{"q":"wwx5N4","w":2702,"e":"199,74","r":["2702"],"t":{"allObject":{}}},"sn0W0a":{"q":"sn0W0a","w":2501,"e":"199,75","r":["2501"],"t":{"allObject":{}}}}}